<root>
  <document>
    <sentences>
      <sentence section="title" type="title" id="1">
        <tokens>
          <token id="1">
            <word>Brussels</word>
            <lemma>Brussels</lemma>
            <CharacterOffsetBegin>0</CharacterOffsetBegin>
            <CharacterOffsetEnd>8</CharacterOffsetEnd>
            <POS>NNP</POS>
            <deprel>nsubj</deprel>
            <deprel_head_id>2</deprel_head_id>
            <deprel_head_text>launches</deprel_head_text>
            <ner>S-GPE</ner>
          </token>
          <token id="2">
            <word>launches</word>
            <lemma>launch</lemma>
            <CharacterOffsetBegin>9</CharacterOffsetBegin>
            <CharacterOffsetEnd>17</CharacterOffsetEnd>
            <POS>VBZ</POS>
            <deprel>root</deprel>
            <deprel_head_id>0</deprel_head_id>
            <deprel_head_text>root</deprel_head_text>
            <ner>O</ner>
          </token>
          <token id="3">
            <word>new</word>
            <lemma>new</lemma>
            <CharacterOffsetBegin>18</CharacterOffsetBegin>
            <CharacterOffsetEnd>21</CharacterOffsetEnd>
            <POS>JJ</POS>
            <deprel>amod</deprel>
            <deprel_head_id>6</deprel_head_id>
            <deprel_head_text>app</deprel_head_text>
            <ner>O</ner>
          </token>
          <token id="4">
            <word>perishables</word>
            <lemma>perishable</lemma>
            <CharacterOffsetBegin>22</CharacterOffsetBegin>
            <CharacterOffsetEnd>33</CharacterOffsetEnd>
            <POS>NNS</POS>
            <deprel>compound</deprel>
            <deprel_head_id>6</deprel_head_id>
            <deprel_head_text>app</deprel_head_text>
            <ner>O</ner>
          </token>
          <token id="5">
            <word>management</word>
            <lemma>management</lemma>
            <CharacterOffsetBegin>34</CharacterOffsetBegin>
            <CharacterOffsetEnd>44</CharacterOffsetEnd>
            <POS>NN</POS>
            <deprel>compound</deprel>
            <deprel_head_id>6</deprel_head_id>
            <deprel_head_text>app</deprel_head_text>
            <ner>O</ner>
          </token>
          <token id="6">
            <word>app</word>
            <lemma>app</lemma>
            <CharacterOffsetBegin>45</CharacterOffsetBegin>
            <CharacterOffsetEnd>48</CharacterOffsetEnd>
            <POS>NN</POS>
            <deprel>obj</deprel>
            <deprel_head_id>2</deprel_head_id>
            <deprel_head_text>launches</deprel_head_text>
            <ner>O</ner>
          </token>
          <token id="7">
            <word>on</word>
            <lemma>on</lemma>
            <CharacterOffsetBegin>49</CharacterOffsetBegin>
            <CharacterOffsetEnd>51</CharacterOffsetEnd>
            <POS>IN</POS>
            <deprel>case</deprel>
            <deprel_head_id>8</deprel_head_id>
            <deprel_head_text>BRUCloud</deprel_head_text>
            <ner>O</ner>
          </token>
          <token id="8">
            <word>BRUCloud</word>
            <lemma>Brucloud</lemma>
            <CharacterOffsetBegin>52</CharacterOffsetBegin>
            <CharacterOffsetEnd>60</CharacterOffsetEnd>
            <POS>NNP</POS>
            <deprel>nmod</deprel>
            <deprel_head_id>6</deprel_head_id>
            <deprel_head_text>app</deprel_head_text>
            <ner>S-ORG</ner>
          </token>
        </tokens>
      </sentence>
      <sentence section="content" type="bodyText" id="2">
        <tokens>
          <token id="1">
            <word>Brussels</word>
            <lemma>Brussels</lemma>
            <CharacterOffsetBegin>62</CharacterOffsetBegin>
            <CharacterOffsetEnd>70</CharacterOffsetEnd>
            <POS>NNP</POS>
            <deprel>nsubj</deprel>
            <deprel_head_id>9</deprel_head_id>
            <deprel_head_text>advanced</deprel_head_text>
            <ner>B-ORG</ner>
          </token>
          <token id="2">
            <word>Airport</word>
            <lemma>Airport</lemma>
            <CharacterOffsetBegin>71</CharacterOffsetBegin>
            <CharacterOffsetEnd>78</CharacterOffsetEnd>
            <POS>NNP</POS>
            <deprel>flat</deprel>
            <deprel_head_id>1</deprel_head_id>
            <deprel_head_text>Brussels</deprel_head_text>
            <ner>I-ORG</ner>
          </token>
          <token id="3">
            <word>'s</word>
            <lemma>'s</lemma>
            <CharacterOffsetBegin>78</CharacterOffsetBegin>
            <CharacterOffsetEnd>80</CharacterOffsetEnd>
            <POS>POS</POS>
            <deprel>case</deprel>
            <deprel_head_id>1</deprel_head_id>
            <deprel_head_text>Brussels</deprel_head_text>
            <ner>E-ORG</ner>
          </token>
          <token id="4">
            <word>(</word>
            <lemma>(</lemma>
            <CharacterOffsetBegin>81</CharacterOffsetBegin>
            <CharacterOffsetEnd>82</CharacterOffsetEnd>
            <POS>-LRB-</POS>
            <deprel>punct</deprel>
            <deprel_head_id>5</deprel_head_id>
            <deprel_head_text>BRU</deprel_head_text>
            <ner>O</ner>
          </token>
          <token id="5">
            <word>BRU</word>
            <lemma>Bru</lemma>
            <CharacterOffsetBegin>82</CharacterOffsetBegin>
            <CharacterOffsetEnd>85</CharacterOffsetEnd>
            <POS>NNP</POS>
            <deprel>appos</deprel>
            <deprel_head_id>1</deprel_head_id>
            <deprel_head_text>Brussels</deprel_head_text>
            <ner>S-ORG</ner>
          </token>
          <token id="6">
            <word>)</word>
            <lemma>)</lemma>
            <CharacterOffsetBegin>85</CharacterOffsetBegin>
            <CharacterOffsetEnd>86</CharacterOffsetEnd>
            <POS>-RRB-</POS>
            <deprel>punct</deprel>
            <deprel_head_id>5</deprel_head_id>
            <deprel_head_text>BRU</deprel_head_text>
            <ner>O</ner>
          </token>
          <token id="7">
            <word>cargo</word>
            <lemma>cargo</lemma>
            <CharacterOffsetBegin>87</CharacterOffsetBegin>
            <CharacterOffsetEnd>92</CharacterOffsetEnd>
            <POS>NN</POS>
            <deprel>compound</deprel>
            <deprel_head_id>8</deprel_head_id>
            <deprel_head_text>division</deprel_head_text>
            <ner>O</ner>
          </token>
          <token id="8">
            <word>division</word>
            <lemma>division</lemma>
            <CharacterOffsetBegin>93</CharacterOffsetBegin>
            <CharacterOffsetEnd>101</CharacterOffsetEnd>
            <POS>NN</POS>
            <deprel>nsubj</deprel>
            <deprel_head_id>9</deprel_head_id>
            <deprel_head_text>advanced</deprel_head_text>
            <ner>O</ner>
          </token>
          <token id="9">
            <word>advanced</word>
            <lemma>advance</lemma>
            <CharacterOffsetBegin>102</CharacterOffsetBegin>
            <CharacterOffsetEnd>110</CharacterOffsetEnd>
            <POS>VBD</POS>
            <deprel>root</deprel>
            <deprel_head_id>0</deprel_head_id>
            <deprel_head_text>root</deprel_head_text>
            <ner>O</ner>
          </token>
          <token id="10">
            <word>its</word>
            <lemma>it</lemma>
            <CharacterOffsetBegin>111</CharacterOffsetBegin>
            <CharacterOffsetEnd>114</CharacterOffsetEnd>
            <POS>PRP$</POS>
            <deprel>nmod:poss</deprel>
            <deprel_head_id>14</deprel_head_id>
            <deprel_head_text>capabilities</deprel_head_text>
            <ner>O</ner>
          </token>
          <token id="11">
            <word>digital</word>
            <lemma>digital</lemma>
            <CharacterOffsetBegin>115</CharacterOffsetBegin>
            <CharacterOffsetEnd>122</CharacterOffsetEnd>
            <POS>JJ</POS>
            <deprel>amod</deprel>
            <deprel_head_id>14</deprel_head_id>
            <deprel_head_text>capabilities</deprel_head_text>
            <ner>O</ner>
          </token>
          <token id="12">
            <word>and</word>
            <lemma>and</lemma>
            <CharacterOffsetBegin>123</CharacterOffsetBegin>
            <CharacterOffsetEnd>126</CharacterOffsetEnd>
            <POS>CC</POS>
            <deprel>cc</deprel>
            <deprel_head_id>13</deprel_head_id>
            <deprel_head_text>perishable</deprel_head_text>
            <ner>O</ner>
          </token>
          <token id="13">
            <word>perishable</word>
            <lemma>perishable</lemma>
            <CharacterOffsetBegin>127</CharacterOffsetBegin>
            <CharacterOffsetEnd>137</CharacterOffsetEnd>
            <POS>JJ</POS>
            <deprel>conj</deprel>
            <deprel_head_id>11</deprel_head_id>
            <deprel_head_text>digital</deprel_head_text>
            <ner>O</ner>
          </token>
          <token id="14">
            <word>capabilities</word>
            <lemma>capability</lemma>
            <CharacterOffsetBegin>138</CharacterOffsetBegin>
            <CharacterOffsetEnd>150</CharacterOffsetEnd>
            <POS>NNS</POS>
            <deprel>obj</deprel>
            <deprel_head_id>9</deprel_head_id>
            <deprel_head_text>advanced</deprel_head_text>
            <ner>O</ner>
          </token>
          <token id="15">
            <word>today</word>
            <lemma>today</lemma>
            <CharacterOffsetBegin>151</CharacterOffsetBegin>
            <CharacterOffsetEnd>156</CharacterOffsetEnd>
            <POS>NN</POS>
            <deprel>obl</deprel>
            <deprel_head_id>9</deprel_head_id>
            <deprel_head_text>advanced</deprel_head_text>
            <ner>S-DATE</ner>
          </token>
          <token id="16">
            <word>with</word>
            <lemma>with</lemma>
            <CharacterOffsetBegin>157</CharacterOffsetBegin>
            <CharacterOffsetEnd>161</CharacterOffsetEnd>
            <POS>IN</POS>
            <deprel>case</deprel>
            <deprel_head_id>19</deprel_head_id>
            <deprel_head_text>launch</deprel_head_text>
            <ner>O</ner>
          </token>
          <token id="17">
            <word>the</word>
            <lemma>the</lemma>
            <CharacterOffsetBegin>162</CharacterOffsetBegin>
            <CharacterOffsetEnd>165</CharacterOffsetEnd>
            <POS>DT</POS>
            <deprel>det</deprel>
            <deprel_head_id>19</deprel_head_id>
            <deprel_head_text>launch</deprel_head_text>
            <ner>O</ner>
          </token>
          <token id="18">
            <word>pilot</word>
            <lemma>pilot</lemma>
            <CharacterOffsetBegin>166</CharacterOffsetBegin>
            <CharacterOffsetEnd>171</CharacterOffsetEnd>
            <POS>NN</POS>
            <deprel>compound</deprel>
            <deprel_head_id>19</deprel_head_id>
            <deprel_head_text>launch</deprel_head_text>
            <ner>O</ner>
          </token>
          <token id="19">
            <word>launch</word>
            <lemma>launch</lemma>
            <CharacterOffsetBegin>172</CharacterOffsetBegin>
            <CharacterOffsetEnd>178</CharacterOffsetEnd>
            <POS>NN</POS>
            <deprel>obl</deprel>
            <deprel_head_id>9</deprel_head_id>
            <deprel_head_text>advanced</deprel_head_text>
            <ner>O</ner>
          </token>
          <token id="20">
            <word>of</word>
            <lemma>of</lemma>
            <CharacterOffsetBegin>179</CharacterOffsetBegin>
            <CharacterOffsetEnd>181</CharacterOffsetEnd>
            <POS>IN</POS>
            <deprel>case</deprel>
            <deprel_head_id>26</deprel_head_id>
            <deprel_head_text>App</deprel_head_text>
            <ner>O</ner>
          </token>
          <token id="21">
            <word>a</word>
            <lemma>a</lemma>
            <CharacterOffsetBegin>182</CharacterOffsetBegin>
            <CharacterOffsetEnd>183</CharacterOffsetEnd>
            <POS>DT</POS>
            <deprel>det</deprel>
            <deprel_head_id>24</deprel_head_id>
            <deprel_head_text>Perishable</deprel_head_text>
            <ner>O</ner>
          </token>
          <token id="22">
            <word>digital</word>
            <lemma>digital</lemma>
            <CharacterOffsetBegin>184</CharacterOffsetBegin>
            <CharacterOffsetEnd>191</CharacterOffsetEnd>
            <POS>JJ</POS>
            <deprel>amod</deprel>
            <deprel_head_id>24</deprel_head_id>
            <deprel_head_text>Perishable</deprel_head_text>
            <ner>O</ner>
          </token>
          <token id="23">
            <word>"</word>
            <lemma>&amp;quot;</lemma>
            <CharacterOffsetBegin>192</CharacterOffsetBegin>
            <CharacterOffsetEnd>193</CharacterOffsetEnd>
            <POS>``</POS>
            <deprel>punct</deprel>
            <deprel_head_id>24</deprel_head_id>
            <deprel_head_text>Perishable</deprel_head_text>
            <ner>O</ner>
          </token>
          <token id="24">
            <word>Perishable</word>
            <lemma>Perishable</lemma>
            <CharacterOffsetBegin>193</CharacterOffsetBegin>
            <CharacterOffsetEnd>203</CharacterOffsetEnd>
            <POS>NNP</POS>
            <deprel>nmod</deprel>
            <deprel_head_id>19</deprel_head_id>
            <deprel_head_text>launch</deprel_head_text>
            <ner>B-PRODUCT</ner>
          </token>
          <token id="25">
            <word>Management</word>
            <lemma>Management</lemma>
            <CharacterOffsetBegin>204</CharacterOffsetBegin>
            <CharacterOffsetEnd>214</CharacterOffsetEnd>
            <POS>NNP</POS>
            <deprel>flat</deprel>
            <deprel_head_id>24</deprel_head_id>
            <deprel_head_text>Perishable</deprel_head_text>
            <ner>I-PRODUCT</ner>
          </token>
          <token id="26">
            <word>App</word>
            <lemma>App</lemma>
            <CharacterOffsetBegin>215</CharacterOffsetBegin>
            <CharacterOffsetEnd>218</CharacterOffsetEnd>
            <POS>NNP</POS>
            <deprel>flat</deprel>
            <deprel_head_id>24</deprel_head_id>
            <deprel_head_text>Perishable</deprel_head_text>
            <ner>I-PRODUCT</ner>
          </token>
          <token id="27">
            <word>"</word>
            <lemma>&amp;quot;</lemma>
            <CharacterOffsetBegin>218</CharacterOffsetBegin>
            <CharacterOffsetEnd>219</CharacterOffsetEnd>
            <POS>''</POS>
            <deprel>punct</deprel>
            <deprel_head_id>26</deprel_head_id>
            <deprel_head_text>App</deprel_head_text>
            <ner>E-PRODUCT</ner>
          </token>
          <token id="28">
            <word>on</word>
            <lemma>on</lemma>
            <CharacterOffsetBegin>220</CharacterOffsetBegin>
            <CharacterOffsetEnd>222</CharacterOffsetEnd>
            <POS>IN</POS>
            <deprel>case</deprel>
            <deprel_head_id>34</deprel_head_id>
            <deprel_head_text>platform</deprel_head_text>
            <ner>O</ner>
          </token>
          <token id="29">
            <word>its</word>
            <lemma>it</lemma>
            <CharacterOffsetBegin>223</CharacterOffsetBegin>
            <CharacterOffsetEnd>226</CharacterOffsetEnd>
            <POS>PRP$</POS>
            <deprel>nmod:poss</deprel>
            <deprel_head_id>34</deprel_head_id>
            <deprel_head_text>platform</deprel_head_text>
            <ner>O</ner>
          </token>
          <token id="30">
            <word>open</word>
            <lemma>open</lemma>
            <CharacterOffsetBegin>227</CharacterOffsetBegin>
            <CharacterOffsetEnd>231</CharacterOffsetEnd>
            <POS>JJ</POS>
            <deprel>amod</deprel>
            <deprel_head_id>31</deprel_head_id>
            <deprel_head_text>data</deprel_head_text>
            <ner>O</ner>
          </token>
          <token id="31">
            <word>data</word>
            <lemma>data</lemma>
            <CharacterOffsetBegin>232</CharacterOffsetBegin>
            <CharacterOffsetEnd>236</CharacterOffsetEnd>
            <POS>NNS</POS>
            <deprel>compound</deprel>
            <deprel_head_id>32</deprel_head_id>
            <deprel_head_text>sharing</deprel_head_text>
            <ner>O</ner>
          </token>
          <token id="32">
            <word>sharing</word>
            <lemma>share</lemma>
            <CharacterOffsetBegin>237</CharacterOffsetBegin>
            <CharacterOffsetEnd>244</CharacterOffsetEnd>
            <POS>VBG</POS>
            <deprel>conj</deprel>
            <deprel_head_id>26</deprel_head_id>
            <deprel_head_text>App</deprel_head_text>
            <ner>O</ner>
          </token>
          <token id="33">
            <word>BRUCloud</word>
            <lemma>Brucloud</lemma>
            <CharacterOffsetBegin>245</CharacterOffsetBegin>
            <CharacterOffsetEnd>253</CharacterOffsetEnd>
            <POS>NNP</POS>
            <deprel>compound</deprel>
            <deprel_head_id>34</deprel_head_id>
            <deprel_head_text>platform</deprel_head_text>
            <ner>S-PRODUCT</ner>
          </token>
          <token id="34">
            <word>platform</word>
            <lemma>platform</lemma>
            <CharacterOffsetBegin>254</CharacterOffsetBegin>
            <CharacterOffsetEnd>262</CharacterOffsetEnd>
            <POS>NN</POS>
            <deprel>obj</deprel>
            <deprel_head_id>32</deprel_head_id>
            <deprel_head_text>sharing</deprel_head_text>
            <ner>O</ner>
          </token>
          <token id="35">
            <word>.</word>
            <lemma>.</lemma>
            <CharacterOffsetBegin>262</CharacterOffsetBegin>
            <CharacterOffsetEnd>263</CharacterOffsetEnd>
            <POS>.</POS>
            <deprel>punct</deprel>
            <deprel_head_id>32</deprel_head_id>
            <deprel_head_text>sharing</deprel_head_text>
            <ner>O</ner>
          </token>
        </tokens>
      </sentence>
      <sentence section="content" type="bodyText" id="3">
        <tokens>
          <token id="1">
            <word>The</word>
            <lemma>the</lemma>
            <CharacterOffsetBegin>264</CharacterOffsetBegin>
            <CharacterOffsetEnd>267</CharacterOffsetEnd>
            <POS>DT</POS>
            <deprel>det</deprel>
            <deprel_head_id>5</deprel_head_id>
            <deprel_head_text>application</deprel_head_text>
            <ner>O</ner>
          </token>
          <token id="2">
            <word>new</word>
            <lemma>new</lemma>
            <CharacterOffsetBegin>268</CharacterOffsetBegin>
            <CharacterOffsetEnd>271</CharacterOffsetEnd>
            <POS>JJ</POS>
            <deprel>amod</deprel>
            <deprel_head_id>5</deprel_head_id>
            <deprel_head_text>application</deprel_head_text>
            <ner>O</ner>
          </token>
          <token id="3">
            <word>Perishable</word>
            <lemma>Perishable</lemma>
            <CharacterOffsetBegin>272</CharacterOffsetBegin>
            <CharacterOffsetEnd>282</CharacterOffsetEnd>
            <POS>NNP</POS>
            <deprel>compound</deprel>
            <deprel_head_id>5</deprel_head_id>
            <deprel_head_text>application</deprel_head_text>
            <ner>B-ORG</ner>
          </token>
          <token id="4">
            <word>Management</word>
            <lemma>Management</lemma>
            <CharacterOffsetBegin>283</CharacterOffsetBegin>
            <CharacterOffsetEnd>293</CharacterOffsetEnd>
            <POS>NNP</POS>
            <deprel>flat</deprel>
            <deprel_head_id>3</deprel_head_id>
            <deprel_head_text>Perishable</deprel_head_text>
            <ner>E-ORG</ner>
          </token>
          <token id="5">
            <word>application</word>
            <lemma>application</lemma>
            <CharacterOffsetBegin>294</CharacterOffsetBegin>
            <CharacterOffsetEnd>305</CharacterOffsetEnd>
            <POS>NN</POS>
            <deprel>nsubj</deprel>
            <deprel_head_id>7</deprel_head_id>
            <deprel_head_text>intended</deprel_head_text>
            <ner>O</ner>
          </token>
          <token id="6">
            <word>is</word>
            <lemma>be</lemma>
            <CharacterOffsetBegin>306</CharacterOffsetBegin>
            <CharacterOffsetEnd>308</CharacterOffsetEnd>
            <POS>VBZ</POS>
            <deprel>aux</deprel>
            <deprel_head_id>7</deprel_head_id>
            <deprel_head_text>intended</deprel_head_text>
            <ner>O</ner>
          </token>
          <token id="7">
            <word>intended</word>
            <lemma>intended</lemma>
            <CharacterOffsetBegin>309</CharacterOffsetBegin>
            <CharacterOffsetEnd>317</CharacterOffsetEnd>
            <POS>VBN</POS>
            <deprel>root</deprel>
            <deprel_head_id>0</deprel_head_id>
            <deprel_head_text>root</deprel_head_text>
            <ner>O</ner>
          </token>
          <token id="8">
            <word>to</word>
            <lemma>to</lemma>
            <CharacterOffsetBegin>318</CharacterOffsetBegin>
            <CharacterOffsetEnd>320</CharacterOffsetEnd>
            <POS>TO</POS>
            <deprel>mark</deprel>
            <deprel_head_id>9</deprel_head_id>
            <deprel_head_text>simplify</deprel_head_text>
            <ner>O</ner>
          </token>
          <token id="9">
            <word>simplify</word>
            <lemma>simplify</lemma>
            <CharacterOffsetBegin>321</CharacterOffsetBegin>
            <CharacterOffsetEnd>329</CharacterOffsetEnd>
            <POS>VB</POS>
            <deprel>xcomp</deprel>
            <deprel_head_id>7</deprel_head_id>
            <deprel_head_text>intended</deprel_head_text>
            <ner>O</ner>
          </token>
          <token id="10">
            <word>work</word>
            <lemma>work</lemma>
            <CharacterOffsetBegin>330</CharacterOffsetBegin>
            <CharacterOffsetEnd>334</CharacterOffsetEnd>
            <POS>NN</POS>
            <deprel>obj</deprel>
            <deprel_head_id>9</deprel_head_id>
            <deprel_head_text>simplify</deprel_head_text>
            <ner>O</ner>
          </token>
          <token id="11">
            <word>for</word>
            <lemma>for</lemma>
            <CharacterOffsetBegin>335</CharacterOffsetBegin>
            <CharacterOffsetEnd>338</CharacterOffsetEnd>
            <POS>IN</POS>
            <deprel>case</deprel>
            <deprel_head_id>15</deprel_head_id>
            <deprel_head_text>Agency</deprel_head_text>
            <ner>O</ner>
          </token>
          <token id="12">
            <word>the</word>
            <lemma>the</lemma>
            <CharacterOffsetBegin>339</CharacterOffsetBegin>
            <CharacterOffsetEnd>342</CharacterOffsetEnd>
            <POS>DT</POS>
            <deprel>det</deprel>
            <deprel_head_id>15</deprel_head_id>
            <deprel_head_text>Agency</deprel_head_text>
            <ner>B-ORG</ner>
          </token>
          <token id="13">
            <word>Belgian</word>
            <lemma>Belgian</lemma>
            <CharacterOffsetBegin>343</CharacterOffsetBegin>
            <CharacterOffsetEnd>350</CharacterOffsetEnd>
            <POS>NNP</POS>
            <deprel>nmod</deprel>
            <deprel_head_id>10</deprel_head_id>
            <deprel_head_text>work</deprel_head_text>
            <ner>I-ORG</ner>
          </token>
          <token id="14">
            <word>Federal</word>
            <lemma>Federal</lemma>
            <CharacterOffsetBegin>351</CharacterOffsetBegin>
            <CharacterOffsetEnd>358</CharacterOffsetEnd>
            <POS>NNP</POS>
            <deprel>flat</deprel>
            <deprel_head_id>13</deprel_head_id>
            <deprel_head_text>Belgian</deprel_head_text>
            <ner>I-ORG</ner>
          </token>
          <token id="15">
            <word>Agency</word>
            <lemma>agency</lemma>
            <CharacterOffsetBegin>359</CharacterOffsetBegin>
            <CharacterOffsetEnd>365</CharacterOffsetEnd>
            <POS>NNP</POS>
            <deprel>flat</deprel>
            <deprel_head_id>13</deprel_head_id>
            <deprel_head_text>Belgian</deprel_head_text>
            <ner>I-ORG</ner>
          </token>
          <token id="16">
            <word>for</word>
            <lemma>for</lemma>
            <CharacterOffsetBegin>366</CharacterOffsetBegin>
            <CharacterOffsetEnd>369</CharacterOffsetEnd>
            <POS>IN</POS>
            <deprel>case</deprel>
            <deprel_head_id>18</deprel_head_id>
            <deprel_head_text>Safety</deprel_head_text>
            <ner>I-ORG</ner>
          </token>
          <token id="17">
            <word>the</word>
            <lemma>the</lemma>
            <CharacterOffsetBegin>370</CharacterOffsetBegin>
            <CharacterOffsetEnd>373</CharacterOffsetEnd>
            <POS>DT</POS>
            <deprel>det</deprel>
            <deprel_head_id>18</deprel_head_id>
            <deprel_head_text>Safety</deprel_head_text>
            <ner>I-ORG</ner>
          </token>
          <token id="18">
            <word>Safety</word>
            <lemma>Safety</lemma>
            <CharacterOffsetBegin>374</CharacterOffsetBegin>
            <CharacterOffsetEnd>380</CharacterOffsetEnd>
            <POS>NNP</POS>
            <deprel>obl</deprel>
            <deprel_head_id>9</deprel_head_id>
            <deprel_head_text>simplify</deprel_head_text>
            <ner>I-ORG</ner>
          </token>
          <token id="19">
            <word>of</word>
            <lemma>of</lemma>
            <CharacterOffsetBegin>381</CharacterOffsetBegin>
            <CharacterOffsetEnd>383</CharacterOffsetEnd>
            <POS>IN</POS>
            <deprel>case</deprel>
            <deprel_head_id>22</deprel_head_id>
            <deprel_head_text>Chain</deprel_head_text>
            <ner>I-ORG</ner>
          </token>
          <token id="20">
            <word>the</word>
            <lemma>the</lemma>
            <CharacterOffsetBegin>384</CharacterOffsetBegin>
            <CharacterOffsetEnd>387</CharacterOffsetEnd>
            <POS>DT</POS>
            <deprel>det</deprel>
            <deprel_head_id>22</deprel_head_id>
            <deprel_head_text>Chain</deprel_head_text>
            <ner>I-ORG</ner>
          </token>
          <token id="21">
            <word>Food</word>
            <lemma>Food</lemma>
            <CharacterOffsetBegin>388</CharacterOffsetBegin>
            <CharacterOffsetEnd>392</CharacterOffsetEnd>
            <POS>NNP</POS>
            <deprel>nmod</deprel>
            <deprel_head_id>18</deprel_head_id>
            <deprel_head_text>Safety</deprel_head_text>
            <ner>I-ORG</ner>
          </token>
          <token id="22">
            <word>Chain</word>
            <lemma>Chain</lemma>
            <CharacterOffsetBegin>393</CharacterOffsetBegin>
            <CharacterOffsetEnd>398</CharacterOffsetEnd>
            <POS>NNP</POS>
            <deprel>flat</deprel>
            <deprel_head_id>21</deprel_head_id>
            <deprel_head_text>Food</deprel_head_text>
            <ner>E-ORG</ner>
          </token>
          <token id="23">
            <word>(</word>
            <lemma>(</lemma>
            <CharacterOffsetBegin>399</CharacterOffsetBegin>
            <CharacterOffsetEnd>400</CharacterOffsetEnd>
            <POS>-LRB-</POS>
            <deprel>punct</deprel>
            <deprel_head_id>24</deprel_head_id>
            <deprel_head_text>FASFC</deprel_head_text>
            <ner>O</ner>
          </token>
          <token id="24">
            <word>FASFC</word>
            <lemma>FASFC</lemma>
            <CharacterOffsetBegin>400</CharacterOffsetBegin>
            <CharacterOffsetEnd>405</CharacterOffsetEnd>
            <POS>NNP</POS>
            <deprel>appos</deprel>
            <deprel_head_id>22</deprel_head_id>
            <deprel_head_text>Chain</deprel_head_text>
            <ner>S-ORG</ner>
          </token>
          <token id="25">
            <word>)</word>
            <lemma>)</lemma>
            <CharacterOffsetBegin>405</CharacterOffsetBegin>
            <CharacterOffsetEnd>406</CharacterOffsetEnd>
            <POS>-RRB-</POS>
            <deprel>punct</deprel>
            <deprel_head_id>24</deprel_head_id>
            <deprel_head_text>FASFC</deprel_head_text>
            <ner>O</ner>
          </token>
          <token id="26">
            <word>and</word>
            <lemma>and</lemma>
            <CharacterOffsetBegin>407</CharacterOffsetBegin>
            <CharacterOffsetEnd>410</CharacterOffsetEnd>
            <POS>CC</POS>
            <deprel>cc</deprel>
            <deprel_head_id>27</deprel_head_id>
            <deprel_head_text>forwarders</deprel_head_text>
            <ner>O</ner>
          </token>
          <token id="27">
            <word>forwarders</word>
            <lemma>forwarder</lemma>
            <CharacterOffsetBegin>411</CharacterOffsetBegin>
            <CharacterOffsetEnd>421</CharacterOffsetEnd>
            <POS>NNS</POS>
            <deprel>conj</deprel>
            <deprel_head_id>22</deprel_head_id>
            <deprel_head_text>Chain</deprel_head_text>
            <ner>O</ner>
          </token>
          <token id="28">
            <word>by</word>
            <lemma>by</lemma>
            <CharacterOffsetBegin>422</CharacterOffsetBegin>
            <CharacterOffsetEnd>424</CharacterOffsetEnd>
            <POS>IN</POS>
            <deprel>mark</deprel>
            <deprel_head_id>29</deprel_head_id>
            <deprel_head_text>offering</deprel_head_text>
            <ner>O</ner>
          </token>
          <token id="29">
            <word>offering</word>
            <lemma>offer</lemma>
            <CharacterOffsetBegin>425</CharacterOffsetBegin>
            <CharacterOffsetEnd>433</CharacterOffsetEnd>
            <POS>VBG</POS>
            <deprel>advcl</deprel>
            <deprel_head_id>9</deprel_head_id>
            <deprel_head_text>simplify</deprel_head_text>
            <ner>O</ner>
          </token>
          <token id="30">
            <word>a</word>
            <lemma>a</lemma>
            <CharacterOffsetBegin>434</CharacterOffsetBegin>
            <CharacterOffsetEnd>435</CharacterOffsetEnd>
            <POS>DT</POS>
            <deprel>det</deprel>
            <deprel_head_id>34</deprel_head_id>
            <deprel_head_text>platform</deprel_head_text>
            <ner>O</ner>
          </token>
          <token id="31">
            <word>central</word>
            <lemma>central</lemma>
            <CharacterOffsetBegin>436</CharacterOffsetBegin>
            <CharacterOffsetEnd>443</CharacterOffsetEnd>
            <POS>JJ</POS>
            <deprel>amod</deprel>
            <deprel_head_id>34</deprel_head_id>
            <deprel_head_text>platform</deprel_head_text>
            <ner>O</ner>
          </token>
          <token id="32">
            <word>,</word>
            <lemma>,</lemma>
            <CharacterOffsetBegin>443</CharacterOffsetBegin>
            <CharacterOffsetEnd>444</CharacterOffsetEnd>
            <POS>,</POS>
            <deprel>punct</deprel>
            <deprel_head_id>31</deprel_head_id>
            <deprel_head_text>central</deprel_head_text>
            <ner>O</ner>
          </token>
          <token id="33">
            <word>digital</word>
            <lemma>digital</lemma>
            <CharacterOffsetBegin>445</CharacterOffsetBegin>
            <CharacterOffsetEnd>452</CharacterOffsetEnd>
            <POS>JJ</POS>
            <deprel>amod</deprel>
            <deprel_head_id>34</deprel_head_id>
            <deprel_head_text>platform</deprel_head_text>
            <ner>O</ner>
          </token>
          <token id="34">
            <word>platform</word>
            <lemma>platform</lemma>
            <CharacterOffsetBegin>453</CharacterOffsetBegin>
            <CharacterOffsetEnd>461</CharacterOffsetEnd>
            <POS>NN</POS>
            <deprel>obj</deprel>
            <deprel_head_id>29</deprel_head_id>
            <deprel_head_text>offering</deprel_head_text>
            <ner>O</ner>
          </token>
          <token id="35">
            <word>for</word>
            <lemma>for</lemma>
            <CharacterOffsetBegin>462</CharacterOffsetBegin>
            <CharacterOffsetEnd>465</CharacterOffsetEnd>
            <POS>IN</POS>
            <deprel>case</deprel>
            <deprel_head_id>40</deprel_head_id>
            <deprel_head_text>exchange</deprel_head_text>
            <ner>O</ner>
          </token>
          <token id="36">
            <word>all</word>
            <lemma>all</lemma>
            <CharacterOffsetBegin>466</CharacterOffsetBegin>
            <CharacterOffsetEnd>469</CharacterOffsetEnd>
            <POS>DT</POS>
            <deprel>det</deprel>
            <deprel_head_id>37</deprel_head_id>
            <deprel_head_text>communication</deprel_head_text>
            <ner>O</ner>
          </token>
          <token id="37">
            <word>communication</word>
            <lemma>communication</lemma>
            <CharacterOffsetBegin>470</CharacterOffsetBegin>
            <CharacterOffsetEnd>483</CharacterOffsetEnd>
            <POS>NN</POS>
            <deprel>compound</deprel>
            <deprel_head_id>40</deprel_head_id>
            <deprel_head_text>exchange</deprel_head_text>
            <ner>O</ner>
          </token>
          <token id="38">
            <word>and</word>
            <lemma>and</lemma>
            <CharacterOffsetBegin>484</CharacterOffsetBegin>
            <CharacterOffsetEnd>487</CharacterOffsetEnd>
            <POS>CC</POS>
            <deprel>cc</deprel>
            <deprel_head_id>39</deprel_head_id>
            <deprel_head_text>document</deprel_head_text>
            <ner>O</ner>
          </token>
          <token id="39">
            <word>document</word>
            <lemma>document</lemma>
            <CharacterOffsetBegin>488</CharacterOffsetBegin>
            <CharacterOffsetEnd>496</CharacterOffsetEnd>
            <POS>NN</POS>
            <deprel>conj</deprel>
            <deprel_head_id>37</deprel_head_id>
            <deprel_head_text>communication</deprel_head_text>
            <ner>O</ner>
          </token>
          <token id="40">
            <word>exchange</word>
            <lemma>exchange</lemma>
            <CharacterOffsetBegin>497</CharacterOffsetBegin>
            <CharacterOffsetEnd>505</CharacterOffsetEnd>
            <POS>NN</POS>
            <deprel>nsubj</deprel>
            <deprel_head_id>41</deprel_head_id>
            <deprel_head_text>related</deprel_head_text>
            <ner>O</ner>
          </token>
          <token id="41">
            <word>related</word>
            <lemma>relate</lemma>
            <CharacterOffsetBegin>506</CharacterOffsetBegin>
            <CharacterOffsetEnd>513</CharacterOffsetEnd>
            <POS>VBN</POS>
            <deprel>advcl</deprel>
            <deprel_head_id>29</deprel_head_id>
            <deprel_head_text>offering</deprel_head_text>
            <ner>O</ner>
          </token>
          <token id="42">
            <word>to</word>
            <lemma>to</lemma>
            <CharacterOffsetBegin>514</CharacterOffsetBegin>
            <CharacterOffsetEnd>516</CharacterOffsetEnd>
            <POS>TO</POS>
            <deprel>case</deprel>
            <deprel_head_id>45</deprel_head_id>
            <deprel_head_text>process</deprel_head_text>
            <ner>O</ner>
          </token>
          <token id="43">
            <word>the</word>
            <lemma>the</lemma>
            <CharacterOffsetBegin>517</CharacterOffsetBegin>
            <CharacterOffsetEnd>520</CharacterOffsetEnd>
            <POS>DT</POS>
            <deprel>det</deprel>
            <deprel_head_id>45</deprel_head_id>
            <deprel_head_text>process</deprel_head_text>
            <ner>O</ner>
          </token>
          <token id="44">
            <word>inspection</word>
            <lemma>inspection</lemma>
            <CharacterOffsetBegin>521</CharacterOffsetBegin>
            <CharacterOffsetEnd>531</CharacterOffsetEnd>
            <POS>NN</POS>
            <deprel>compound</deprel>
            <deprel_head_id>45</deprel_head_id>
            <deprel_head_text>process</deprel_head_text>
            <ner>O</ner>
          </token>
          <token id="45">
            <word>process</word>
            <lemma>process</lemma>
            <CharacterOffsetBegin>532</CharacterOffsetBegin>
            <CharacterOffsetEnd>539</CharacterOffsetEnd>
            <POS>NN</POS>
            <deprel>obl</deprel>
            <deprel_head_id>41</deprel_head_id>
            <deprel_head_text>related</deprel_head_text>
            <ner>O</ner>
          </token>
          <token id="46">
            <word>of</word>
            <lemma>of</lemma>
            <CharacterOffsetBegin>540</CharacterOffsetBegin>
            <CharacterOffsetEnd>542</CharacterOffsetEnd>
            <POS>IN</POS>
            <deprel>case</deprel>
            <deprel_head_id>47</deprel_head_id>
            <deprel_head_text>perishables</deprel_head_text>
            <ner>O</ner>
          </token>
          <token id="47">
            <word>perishables</word>
            <lemma>perishable</lemma>
            <CharacterOffsetBegin>543</CharacterOffsetBegin>
            <CharacterOffsetEnd>554</CharacterOffsetEnd>
            <POS>NNS</POS>
            <deprel>nmod</deprel>
            <deprel_head_id>45</deprel_head_id>
            <deprel_head_text>process</deprel_head_text>
            <ner>O</ner>
          </token>
          <token id="48">
            <word>.</word>
            <lemma>.</lemma>
            <CharacterOffsetBegin>554</CharacterOffsetBegin>
            <CharacterOffsetEnd>555</CharacterOffsetEnd>
            <POS>.</POS>
            <deprel>punct</deprel>
            <deprel_head_id>7</deprel_head_id>
            <deprel_head_text>intended</deprel_head_text>
            <ner>O</ner>
          </token>
        </tokens>
      </sentence>
      <sentence section="content" type="bodyText" id="4">
        <tokens>
          <token id="1">
            <word>The</word>
            <lemma>the</lemma>
            <CharacterOffsetBegin>556</CharacterOffsetBegin>
            <CharacterOffsetEnd>559</CharacterOffsetEnd>
            <POS>DT</POS>
            <deprel>det</deprel>
            <deprel_head_id>2</deprel_head_id>
            <deprel_head_text>application</deprel_head_text>
            <ner>O</ner>
          </token>
          <token id="2">
            <word>application</word>
            <lemma>application</lemma>
            <CharacterOffsetBegin>560</CharacterOffsetBegin>
            <CharacterOffsetEnd>571</CharacterOffsetEnd>
            <POS>NN</POS>
            <deprel>nsubj</deprel>
            <deprel_head_id>4</deprel_head_id>
            <deprel_head_text>accessible</deprel_head_text>
            <ner>O</ner>
          </token>
          <token id="3">
            <word>is</word>
            <lemma>be</lemma>
            <CharacterOffsetBegin>572</CharacterOffsetBegin>
            <CharacterOffsetEnd>574</CharacterOffsetEnd>
            <POS>VBZ</POS>
            <deprel>cop</deprel>
            <deprel_head_id>4</deprel_head_id>
            <deprel_head_text>accessible</deprel_head_text>
            <ner>O</ner>
          </token>
          <token id="4">
            <word>accessible</word>
            <lemma>accessible</lemma>
            <CharacterOffsetBegin>575</CharacterOffsetBegin>
            <CharacterOffsetEnd>585</CharacterOffsetEnd>
            <POS>JJ</POS>
            <deprel>root</deprel>
            <deprel_head_id>0</deprel_head_id>
            <deprel_head_text>root</deprel_head_text>
            <ner>O</ner>
          </token>
          <token id="5">
            <word>via</word>
            <lemma>via</lemma>
            <CharacterOffsetBegin>586</CharacterOffsetBegin>
            <CharacterOffsetEnd>589</CharacterOffsetEnd>
            <POS>IN</POS>
            <deprel>case</deprel>
            <deprel_head_id>7</deprel_head_id>
            <deprel_head_text>device</deprel_head_text>
            <ner>O</ner>
          </token>
          <token id="6">
            <word>mobile</word>
            <lemma>mobile</lemma>
            <CharacterOffsetBegin>590</CharacterOffsetBegin>
            <CharacterOffsetEnd>596</CharacterOffsetEnd>
            <POS>JJ</POS>
            <deprel>amod</deprel>
            <deprel_head_id>7</deprel_head_id>
            <deprel_head_text>device</deprel_head_text>
            <ner>O</ner>
          </token>
          <token id="7">
            <word>device</word>
            <lemma>device</lemma>
            <CharacterOffsetBegin>597</CharacterOffsetBegin>
            <CharacterOffsetEnd>603</CharacterOffsetEnd>
            <POS>NN</POS>
            <deprel>nmod</deprel>
            <deprel_head_id>4</deprel_head_id>
            <deprel_head_text>accessible</deprel_head_text>
            <ner>O</ner>
          </token>
          <token id="8">
            <word>and</word>
            <lemma>and</lemma>
            <CharacterOffsetBegin>604</CharacterOffsetBegin>
            <CharacterOffsetEnd>607</CharacterOffsetEnd>
            <POS>CC</POS>
            <deprel>cc</deprel>
            <deprel_head_id>11</deprel_head_id>
            <deprel_head_text>allow</deprel_head_text>
            <ner>O</ner>
          </token>
          <token id="9">
            <word>will</word>
            <lemma>will</lemma>
            <CharacterOffsetBegin>608</CharacterOffsetBegin>
            <CharacterOffsetEnd>612</CharacterOffsetEnd>
            <POS>MD</POS>
            <deprel>aux</deprel>
            <deprel_head_id>11</deprel_head_id>
            <deprel_head_text>allow</deprel_head_text>
            <ner>O</ner>
          </token>
          <token id="10">
            <word>also</word>
            <lemma>also</lemma>
            <CharacterOffsetBegin>613</CharacterOffsetBegin>
            <CharacterOffsetEnd>617</CharacterOffsetEnd>
            <POS>RB</POS>
            <deprel>advmod</deprel>
            <deprel_head_id>11</deprel_head_id>
            <deprel_head_text>allow</deprel_head_text>
            <ner>O</ner>
          </token>
          <token id="11">
            <word>allow</word>
            <lemma>allow</lemma>
            <CharacterOffsetBegin>618</CharacterOffsetBegin>
            <CharacterOffsetEnd>623</CharacterOffsetEnd>
            <POS>VB</POS>
            <deprel>conj</deprel>
            <deprel_head_id>4</deprel_head_id>
            <deprel_head_text>accessible</deprel_head_text>
            <ner>O</ner>
          </token>
          <token id="12">
            <word>FASFC</word>
            <lemma>FASFC</lemma>
            <CharacterOffsetBegin>624</CharacterOffsetBegin>
            <CharacterOffsetEnd>629</CharacterOffsetEnd>
            <POS>NNP</POS>
            <deprel>obj</deprel>
            <deprel_head_id>11</deprel_head_id>
            <deprel_head_text>allow</deprel_head_text>
            <ner>S-ORG</ner>
          </token>
          <token id="13">
            <word>and</word>
            <lemma>and</lemma>
            <CharacterOffsetBegin>630</CharacterOffsetBegin>
            <CharacterOffsetEnd>633</CharacterOffsetEnd>
            <POS>CC</POS>
            <deprel>cc</deprel>
            <deprel_head_id>14</deprel_head_id>
            <deprel_head_text>forwarders</deprel_head_text>
            <ner>O</ner>
          </token>
          <token id="14">
            <word>forwarders</word>
            <lemma>forwarder</lemma>
            <CharacterOffsetBegin>634</CharacterOffsetBegin>
            <CharacterOffsetEnd>644</CharacterOffsetEnd>
            <POS>NNS</POS>
            <deprel>conj</deprel>
            <deprel_head_id>12</deprel_head_id>
            <deprel_head_text>FASFC</deprel_head_text>
            <ner>O</ner>
          </token>
          <token id="15">
            <word>the</word>
            <lemma>the</lemma>
            <CharacterOffsetBegin>645</CharacterOffsetBegin>
            <CharacterOffsetEnd>648</CharacterOffsetEnd>
            <POS>DT</POS>
            <deprel>det</deprel>
            <deprel_head_id>16</deprel_head_id>
            <deprel_head_text>ability</deprel_head_text>
            <ner>O</ner>
          </token>
          <token id="16">
            <word>ability</word>
            <lemma>ability</lemma>
            <CharacterOffsetBegin>649</CharacterOffsetBegin>
            <CharacterOffsetEnd>656</CharacterOffsetEnd>
            <POS>NN</POS>
            <deprel>obj</deprel>
            <deprel_head_id>11</deprel_head_id>
            <deprel_head_text>allow</deprel_head_text>
            <ner>O</ner>
          </token>
          <token id="17">
            <word>to</word>
            <lemma>to</lemma>
            <CharacterOffsetBegin>657</CharacterOffsetBegin>
            <CharacterOffsetEnd>659</CharacterOffsetEnd>
            <POS>TO</POS>
            <deprel>mark</deprel>
            <deprel_head_id>18</deprel_head_id>
            <deprel_head_text>track</deprel_head_text>
            <ner>O</ner>
          </token>
          <token id="18">
            <word>track</word>
            <lemma>track</lemma>
            <CharacterOffsetBegin>660</CharacterOffsetBegin>
            <CharacterOffsetEnd>665</CharacterOffsetEnd>
            <POS>VB</POS>
            <deprel>acl</deprel>
            <deprel_head_id>16</deprel_head_id>
            <deprel_head_text>ability</deprel_head_text>
            <ner>O</ner>
          </token>
          <token id="19">
            <word>the</word>
            <lemma>the</lemma>
            <CharacterOffsetBegin>666</CharacterOffsetBegin>
            <CharacterOffsetEnd>669</CharacterOffsetEnd>
            <POS>DT</POS>
            <deprel>det</deprel>
            <deprel_head_id>21</deprel_head_id>
            <deprel_head_text>status</deprel_head_text>
            <ner>O</ner>
          </token>
          <token id="20">
            <word>inspection</word>
            <lemma>inspection</lemma>
            <CharacterOffsetBegin>670</CharacterOffsetBegin>
            <CharacterOffsetEnd>680</CharacterOffsetEnd>
            <POS>NN</POS>
            <deprel>compound</deprel>
            <deprel_head_id>21</deprel_head_id>
            <deprel_head_text>status</deprel_head_text>
            <ner>O</ner>
          </token>
          <token id="21">
            <word>status</word>
            <lemma>status</lemma>
            <CharacterOffsetBegin>681</CharacterOffsetBegin>
            <CharacterOffsetEnd>687</CharacterOffsetEnd>
            <POS>NN</POS>
            <deprel>obj</deprel>
            <deprel_head_id>18</deprel_head_id>
            <deprel_head_text>track</deprel_head_text>
            <ner>O</ner>
          </token>
          <token id="22">
            <word>of</word>
            <lemma>of</lemma>
            <CharacterOffsetBegin>688</CharacterOffsetBegin>
            <CharacterOffsetEnd>690</CharacterOffsetEnd>
            <POS>IN</POS>
            <deprel>case</deprel>
            <deprel_head_id>23</deprel_head_id>
            <deprel_head_text>shipments</deprel_head_text>
            <ner>O</ner>
          </token>
          <token id="23">
            <word>shipments</word>
            <lemma>shipment</lemma>
            <CharacterOffsetBegin>691</CharacterOffsetBegin>
            <CharacterOffsetEnd>700</CharacterOffsetEnd>
            <POS>NNS</POS>
            <deprel>nmod</deprel>
            <deprel_head_id>21</deprel_head_id>
            <deprel_head_text>status</deprel_head_text>
            <ner>O</ner>
          </token>
          <token id="24">
            <word>in</word>
            <lemma>in</lemma>
            <CharacterOffsetBegin>701</CharacterOffsetBegin>
            <CharacterOffsetEnd>703</CharacterOffsetEnd>
            <POS>IN</POS>
            <deprel>case</deprel>
            <deprel_head_id>26</deprel_head_id>
            <deprel_head_text>time</deprel_head_text>
            <ner>O</ner>
          </token>
          <token id="25">
            <word>real</word>
            <lemma>real</lemma>
            <CharacterOffsetBegin>704</CharacterOffsetBegin>
            <CharacterOffsetEnd>708</CharacterOffsetEnd>
            <POS>JJ</POS>
            <deprel>amod</deprel>
            <deprel_head_id>26</deprel_head_id>
            <deprel_head_text>time</deprel_head_text>
            <ner>O</ner>
          </token>
          <token id="26">
            <word>time</word>
            <lemma>time</lemma>
            <CharacterOffsetBegin>709</CharacterOffsetBegin>
            <CharacterOffsetEnd>713</CharacterOffsetEnd>
            <POS>NN</POS>
            <deprel>obl</deprel>
            <deprel_head_id>18</deprel_head_id>
            <deprel_head_text>track</deprel_head_text>
            <ner>O</ner>
          </token>
          <token id="27">
            <word>.</word>
            <lemma>.</lemma>
            <CharacterOffsetBegin>713</CharacterOffsetBegin>
            <CharacterOffsetEnd>714</CharacterOffsetEnd>
            <POS>.</POS>
            <deprel>punct</deprel>
            <deprel_head_id>4</deprel_head_id>
            <deprel_head_text>accessible</deprel_head_text>
            <ner>O</ner>
          </token>
        </tokens>
      </sentence>
      <sentence section="content" type="bodyText" id="5">
        <tokens>
          <token id="1">
            <word>Further</word>
            <lemma>further</lemma>
            <CharacterOffsetBegin>715</CharacterOffsetBegin>
            <CharacterOffsetEnd>722</CharacterOffsetEnd>
            <POS>JJR</POS>
            <deprel>amod</deprel>
            <deprel_head_id>2</deprel_head_id>
            <deprel_head_text>details</deprel_head_text>
            <ner>O</ner>
          </token>
          <token id="2">
            <word>details</word>
            <lemma>detail</lemma>
            <CharacterOffsetBegin>723</CharacterOffsetBegin>
            <CharacterOffsetEnd>730</CharacterOffsetEnd>
            <POS>NNS</POS>
            <deprel>nsubj</deprel>
            <deprel_head_id>12</deprel_head_id>
            <deprel_head_text>forthcoming</deprel_head_text>
            <ner>O</ner>
          </token>
          <token id="3">
            <word>regarding</word>
            <lemma>regard</lemma>
            <CharacterOffsetBegin>731</CharacterOffsetBegin>
            <CharacterOffsetEnd>740</CharacterOffsetEnd>
            <POS>VBG</POS>
            <deprel>root</deprel>
            <deprel_head_id>0</deprel_head_id>
            <deprel_head_text>root</deprel_head_text>
            <ner>O</ner>
          </token>
          <token id="4">
            <word>the</word>
            <lemma>the</lemma>
            <CharacterOffsetBegin>741</CharacterOffsetBegin>
            <CharacterOffsetEnd>744</CharacterOffsetEnd>
            <POS>DT</POS>
            <deprel>det</deprel>
            <deprel_head_id>6</deprel_head_id>
            <deprel_head_text>addition</deprel_head_text>
            <ner>O</ner>
          </token>
          <token id="5">
            <word>new</word>
            <lemma>new</lemma>
            <CharacterOffsetBegin>745</CharacterOffsetBegin>
            <CharacterOffsetEnd>748</CharacterOffsetEnd>
            <POS>JJ</POS>
            <deprel>amod</deprel>
            <deprel_head_id>6</deprel_head_id>
            <deprel_head_text>addition</deprel_head_text>
            <ner>O</ner>
          </token>
          <token id="6">
            <word>addition</word>
            <lemma>addition</lemma>
            <CharacterOffsetBegin>749</CharacterOffsetBegin>
            <CharacterOffsetEnd>757</CharacterOffsetEnd>
            <POS>NN</POS>
            <deprel>obj</deprel>
            <deprel_head_id>3</deprel_head_id>
            <deprel_head_text>regarding</deprel_head_text>
            <ner>O</ner>
          </token>
          <token id="7">
            <word>to</word>
            <lemma>to</lemma>
            <CharacterOffsetBegin>758</CharacterOffsetBegin>
            <CharacterOffsetEnd>760</CharacterOffsetEnd>
            <POS>TO</POS>
            <deprel>case</deprel>
            <deprel_head_id>10</deprel_head_id>
            <deprel_head_text>BRUCloud</deprel_head_text>
            <ner>O</ner>
          </token>
          <token id="8">
            <word>BRU</word>
            <lemma>Bru</lemma>
            <CharacterOffsetBegin>761</CharacterOffsetBegin>
            <CharacterOffsetEnd>764</CharacterOffsetEnd>
            <POS>NNP</POS>
            <deprel>nmod:poss</deprel>
            <deprel_head_id>10</deprel_head_id>
            <deprel_head_text>BRUCloud</deprel_head_text>
            <ner>S-ORG</ner>
          </token>
          <token id="9">
            <word>'s</word>
            <lemma>'s</lemma>
            <CharacterOffsetBegin>764</CharacterOffsetBegin>
            <CharacterOffsetEnd>766</CharacterOffsetEnd>
            <POS>POS</POS>
            <deprel>case</deprel>
            <deprel_head_id>8</deprel_head_id>
            <deprel_head_text>BRU</deprel_head_text>
            <ner>O</ner>
          </token>
          <token id="10">
            <word>BRUCloud</word>
            <lemma>Brucloud</lemma>
            <CharacterOffsetBegin>767</CharacterOffsetBegin>
            <CharacterOffsetEnd>775</CharacterOffsetEnd>
            <POS>NNP</POS>
            <deprel>nmod</deprel>
            <deprel_head_id>6</deprel_head_id>
            <deprel_head_text>addition</deprel_head_text>
            <ner>S-ORG</ner>
          </token>
          <token id="11">
            <word>are</word>
            <lemma>be</lemma>
            <CharacterOffsetBegin>776</CharacterOffsetBegin>
            <CharacterOffsetEnd>779</CharacterOffsetEnd>
            <POS>VBP</POS>
            <deprel>aux</deprel>
            <deprel_head_id>12</deprel_head_id>
            <deprel_head_text>forthcoming</deprel_head_text>
            <ner>O</ner>
          </token>
          <token id="12">
            <word>forthcoming</word>
            <lemma>forthcom</lemma>
            <CharacterOffsetBegin>780</CharacterOffsetBegin>
            <CharacterOffsetEnd>791</CharacterOffsetEnd>
            <POS>VBG</POS>
            <deprel>xcomp</deprel>
            <deprel_head_id>3</deprel_head_id>
            <deprel_head_text>regarding</deprel_head_text>
            <ner>O</ner>
          </token>
          <token id="13">
            <word>.</word>
            <lemma>.</lemma>
            <CharacterOffsetBegin>791</CharacterOffsetBegin>
            <CharacterOffsetEnd>792</CharacterOffsetEnd>
            <POS>.</POS>
            <deprel>punct</deprel>
            <deprel_head_id>12</deprel_head_id>
            <deprel_head_text>forthcoming</deprel_head_text>
            <ner>O</ner>
          </token>
        </tokens>
      </sentence>
    </sentences>
  </document>
</root>
