<root>
  <document>
    <sentences>
      <sentence section="title" type="title" id="1">
        <tokens>
          <token id="1">
            <word>WFS</word>
            <lemma>wf</lemma>
            <CharacterOffsetBegin>0</CharacterOffsetBegin>
            <CharacterOffsetEnd>3</CharacterOffsetEnd>
            <POS>NNS</POS>
          </token>
          <token id="2">
            <word>to</word>
            <lemma>to</lemma>
            <CharacterOffsetBegin>4</CharacterOffsetBegin>
            <CharacterOffsetEnd>6</CharacterOffsetEnd>
            <POS>TO</POS>
          </token>
          <token id="3">
            <word>operate</word>
            <lemma>operate</lemma>
            <CharacterOffsetBegin>7</CharacterOffsetBegin>
            <CharacterOffsetEnd>14</CharacterOffsetEnd>
            <POS>VB</POS>
          </token>
          <token id="4">
            <word>new</word>
            <lemma>new</lemma>
            <CharacterOffsetBegin>15</CharacterOffsetBegin>
            <CharacterOffsetEnd>18</CharacterOffsetEnd>
            <POS>JJ</POS>
          </token>
          <token id="5">
            <word>seafood</word>
            <lemma>seafood</lemma>
            <CharacterOffsetBegin>19</CharacterOffsetBegin>
            <CharacterOffsetEnd>26</CharacterOffsetEnd>
            <POS>NN</POS>
          </token>
          <token id="6">
            <word>centre</word>
            <lemma>centre</lemma>
            <CharacterOffsetBegin>27</CharacterOffsetBegin>
            <CharacterOffsetEnd>33</CharacterOffsetEnd>
            <POS>NN</POS>
          </token>
          <token id="7">
            <word>at</word>
            <lemma>at</lemma>
            <CharacterOffsetBegin>34</CharacterOffsetBegin>
            <CharacterOffsetEnd>36</CharacterOffsetEnd>
            <POS>IN</POS>
          </token>
          <token id="8">
            <word>Oslo</word>
            <lemma>Oslo</lemma>
            <CharacterOffsetBegin>37</CharacterOffsetBegin>
            <CharacterOffsetEnd>41</CharacterOffsetEnd>
            <POS>NNP</POS>
          </token>
          <token id="9">
            <word>Airport</word>
            <lemma>Airport</lemma>
            <CharacterOffsetBegin>42</CharacterOffsetBegin>
            <CharacterOffsetEnd>49</CharacterOffsetEnd>
            <POS>NNP</POS>
          </token>
        </tokens>
      </sentence>
      <sentence section="content" type="bodyText" id="2">
        <tokens>
          <token id="1">
            <word>Worldwide</word>
            <lemma>Worldwide</lemma>
            <CharacterOffsetBegin>0</CharacterOffsetBegin>
            <CharacterOffsetEnd>9</CharacterOffsetEnd>
            <POS>NNP</POS>
          </token>
          <token id="2">
            <word>Flight</word>
            <lemma>Flight</lemma>
            <CharacterOffsetBegin>10</CharacterOffsetBegin>
            <CharacterOffsetEnd>16</CharacterOffsetEnd>
            <POS>NNP</POS>
          </token>
          <token id="3">
            <word>Services</word>
            <lemma>Services</lemma>
            <CharacterOffsetBegin>17</CharacterOffsetBegin>
            <CharacterOffsetEnd>25</CharacterOffsetEnd>
            <POS>NNP</POS>
          </token>
          <token id="4">
            <word>-LRB-</word>
            <lemma>-lrb-</lemma>
            <CharacterOffsetBegin>26</CharacterOffsetBegin>
            <CharacterOffsetEnd>27</CharacterOffsetEnd>
            <POS>-LRB-</POS>
          </token>
          <token id="5">
            <word>WFS</word>
            <lemma>WFS</lemma>
            <CharacterOffsetBegin>27</CharacterOffsetBegin>
            <CharacterOffsetEnd>30</CharacterOffsetEnd>
            <POS>NNP</POS>
          </token>
          <token id="6">
            <word>-RRB-</word>
            <lemma>-rrb-</lemma>
            <CharacterOffsetBegin>30</CharacterOffsetBegin>
            <CharacterOffsetEnd>31</CharacterOffsetEnd>
            <POS>-RRB-</POS>
          </token>
          <token id="7">
            <word>and</word>
            <lemma>and</lemma>
            <CharacterOffsetBegin>32</CharacterOffsetBegin>
            <CharacterOffsetEnd>35</CharacterOffsetEnd>
            <POS>CC</POS>
          </token>
          <token id="8">
            <word>Sjømatterminalen</word>
            <lemma>Sjømatterminalen</lemma>
            <CharacterOffsetBegin>36</CharacterOffsetBegin>
            <CharacterOffsetEnd>52</CharacterOffsetEnd>
            <POS>NNP</POS>
          </token>
          <token id="9">
            <word>have</word>
            <lemma>have</lemma>
            <CharacterOffsetBegin>53</CharacterOffsetBegin>
            <CharacterOffsetEnd>57</CharacterOffsetEnd>
            <POS>VBP</POS>
          </token>
          <token id="10">
            <word>signed</word>
            <lemma>sign</lemma>
            <CharacterOffsetBegin>58</CharacterOffsetBegin>
            <CharacterOffsetEnd>64</CharacterOffsetEnd>
            <POS>VBN</POS>
          </token>
          <token id="11">
            <word>an</word>
            <lemma>a</lemma>
            <CharacterOffsetBegin>65</CharacterOffsetBegin>
            <CharacterOffsetEnd>67</CharacterOffsetEnd>
            <POS>DT</POS>
          </token>
          <token id="12">
            <word>MOU</word>
            <lemma>mou</lemma>
            <CharacterOffsetBegin>68</CharacterOffsetBegin>
            <CharacterOffsetEnd>71</CharacterOffsetEnd>
            <POS>NN</POS>
          </token>
          <token id="13">
            <word>to</word>
            <lemma>to</lemma>
            <CharacterOffsetBegin>72</CharacterOffsetBegin>
            <CharacterOffsetEnd>74</CharacterOffsetEnd>
            <POS>TO</POS>
          </token>
          <token id="14">
            <word>operate</word>
            <lemma>operate</lemma>
            <CharacterOffsetBegin>75</CharacterOffsetBegin>
            <CharacterOffsetEnd>82</CharacterOffsetEnd>
            <POS>VB</POS>
          </token>
          <token id="15">
            <word>the</word>
            <lemma>the</lemma>
            <CharacterOffsetBegin>83</CharacterOffsetBegin>
            <CharacterOffsetEnd>86</CharacterOffsetEnd>
            <POS>DT</POS>
          </token>
          <token id="16">
            <word>Seafood</word>
            <lemma>Seafood</lemma>
            <CharacterOffsetBegin>87</CharacterOffsetBegin>
            <CharacterOffsetEnd>94</CharacterOffsetEnd>
            <POS>NNP</POS>
          </token>
          <token id="17">
            <word>Centre</word>
            <lemma>Centre</lemma>
            <CharacterOffsetBegin>95</CharacterOffsetBegin>
            <CharacterOffsetEnd>101</CharacterOffsetEnd>
            <POS>NNP</POS>
          </token>
          <token id="18">
            <word>at</word>
            <lemma>at</lemma>
            <CharacterOffsetBegin>102</CharacterOffsetBegin>
            <CharacterOffsetEnd>104</CharacterOffsetEnd>
            <POS>IN</POS>
          </token>
          <token id="19">
            <word>Oslo</word>
            <lemma>Oslo</lemma>
            <CharacterOffsetBegin>105</CharacterOffsetBegin>
            <CharacterOffsetEnd>109</CharacterOffsetEnd>
            <POS>NNP</POS>
          </token>
          <token id="20">
            <word>Airport</word>
            <lemma>Airport</lemma>
            <CharacterOffsetBegin>110</CharacterOffsetBegin>
            <CharacterOffsetEnd>117</CharacterOffsetEnd>
            <POS>NNP</POS>
          </token>
          <token id="21">
            <word>,</word>
            <lemma>,</lemma>
            <CharacterOffsetBegin>117</CharacterOffsetBegin>
            <CharacterOffsetEnd>118</CharacterOffsetEnd>
            <POS>,</POS>
          </token>
          <token id="22">
            <word>which</word>
            <lemma>which</lemma>
            <CharacterOffsetBegin>119</CharacterOffsetBegin>
            <CharacterOffsetEnd>124</CharacterOffsetEnd>
            <POS>WDT</POS>
          </token>
          <token id="23">
            <word>will</word>
            <lemma>will</lemma>
            <CharacterOffsetBegin>125</CharacterOffsetBegin>
            <CharacterOffsetEnd>129</CharacterOffsetEnd>
            <POS>MD</POS>
          </token>
          <token id="24">
            <word>handle</word>
            <lemma>handle</lemma>
            <CharacterOffsetBegin>130</CharacterOffsetBegin>
            <CharacterOffsetEnd>136</CharacterOffsetEnd>
            <POS>VB</POS>
          </token>
          <token id="25">
            <word>up</word>
            <lemma>up</lemma>
            <CharacterOffsetBegin>137</CharacterOffsetBegin>
            <CharacterOffsetEnd>139</CharacterOffsetEnd>
            <POS>RP</POS>
          </token>
          <token id="26">
            <word>to</word>
            <lemma>to</lemma>
            <CharacterOffsetBegin>140</CharacterOffsetBegin>
            <CharacterOffsetEnd>142</CharacterOffsetEnd>
            <POS>TO</POS>
          </token>
          <token id="27">
            <word>250,000</word>
            <lemma>250,000</lemma>
            <CharacterOffsetBegin>143</CharacterOffsetBegin>
            <CharacterOffsetEnd>150</CharacterOffsetEnd>
            <POS>CD</POS>
          </token>
          <token id="28">
            <word>tons</word>
            <lemma>ton</lemma>
            <CharacterOffsetBegin>151</CharacterOffsetBegin>
            <CharacterOffsetEnd>155</CharacterOffsetEnd>
            <POS>NNS</POS>
          </token>
          <token id="29">
            <word>a</word>
            <lemma>a</lemma>
            <CharacterOffsetBegin>156</CharacterOffsetBegin>
            <CharacterOffsetEnd>157</CharacterOffsetEnd>
            <POS>DT</POS>
          </token>
          <token id="30">
            <word>year</word>
            <lemma>year</lemma>
            <CharacterOffsetBegin>158</CharacterOffsetBegin>
            <CharacterOffsetEnd>162</CharacterOffsetEnd>
            <POS>NN</POS>
          </token>
          <token id="31">
            <word>.</word>
            <lemma>.</lemma>
            <CharacterOffsetBegin>162</CharacterOffsetBegin>
            <CharacterOffsetEnd>163</CharacterOffsetEnd>
            <POS>.</POS>
          </token>
        </tokens>
      </sentence>
      <sentence section="content" type="bodyText" id="3">
        <tokens>
          <token id="1">
            <word>Norway</word>
            <lemma>Norway</lemma>
            <CharacterOffsetBegin>0</CharacterOffsetBegin>
            <CharacterOffsetEnd>6</CharacterOffsetEnd>
            <POS>NNP</POS>
          </token>
          <token id="2">
            <word>accounts</word>
            <lemma>account</lemma>
            <CharacterOffsetBegin>7</CharacterOffsetBegin>
            <CharacterOffsetEnd>15</CharacterOffsetEnd>
            <POS>NNS</POS>
          </token>
          <token id="3">
            <word>for</word>
            <lemma>for</lemma>
            <CharacterOffsetBegin>16</CharacterOffsetBegin>
            <CharacterOffsetEnd>19</CharacterOffsetEnd>
            <POS>IN</POS>
          </token>
          <token id="4">
            <word>half</word>
            <lemma>half</lemma>
            <CharacterOffsetBegin>20</CharacterOffsetBegin>
            <CharacterOffsetEnd>24</CharacterOffsetEnd>
            <POS>NN</POS>
          </token>
          <token id="5">
            <word>of</word>
            <lemma>of</lemma>
            <CharacterOffsetBegin>25</CharacterOffsetBegin>
            <CharacterOffsetEnd>27</CharacterOffsetEnd>
            <POS>IN</POS>
          </token>
          <token id="6">
            <word>the</word>
            <lemma>the</lemma>
            <CharacterOffsetBegin>28</CharacterOffsetBegin>
            <CharacterOffsetEnd>31</CharacterOffsetEnd>
            <POS>DT</POS>
          </token>
          <token id="7">
            <word>air</word>
            <lemma>air</lemma>
            <CharacterOffsetBegin>32</CharacterOffsetBegin>
            <CharacterOffsetEnd>35</CharacterOffsetEnd>
            <POS>NN</POS>
          </token>
          <token id="8">
            <word>cargo</word>
            <lemma>cargo</lemma>
            <CharacterOffsetBegin>36</CharacterOffsetBegin>
            <CharacterOffsetEnd>41</CharacterOffsetEnd>
            <POS>NN</POS>
          </token>
          <token id="9">
            <word>generated</word>
            <lemma>generate</lemma>
            <CharacterOffsetBegin>42</CharacterOffsetBegin>
            <CharacterOffsetEnd>51</CharacterOffsetEnd>
            <POS>VBN</POS>
          </token>
          <token id="10">
            <word>in</word>
            <lemma>in</lemma>
            <CharacterOffsetBegin>52</CharacterOffsetBegin>
            <CharacterOffsetEnd>54</CharacterOffsetEnd>
            <POS>IN</POS>
          </token>
          <token id="11">
            <word>the</word>
            <lemma>the</lemma>
            <CharacterOffsetBegin>55</CharacterOffsetBegin>
            <CharacterOffsetEnd>58</CharacterOffsetEnd>
            <POS>DT</POS>
          </token>
          <token id="12">
            <word>Nordic</word>
            <lemma>nordic</lemma>
            <CharacterOffsetBegin>59</CharacterOffsetBegin>
            <CharacterOffsetEnd>65</CharacterOffsetEnd>
            <POS>JJ</POS>
          </token>
          <token id="13">
            <word>region</word>
            <lemma>region</lemma>
            <CharacterOffsetBegin>66</CharacterOffsetBegin>
            <CharacterOffsetEnd>72</CharacterOffsetEnd>
            <POS>NN</POS>
          </token>
          <token id="14">
            <word>,</word>
            <lemma>,</lemma>
            <CharacterOffsetBegin>72</CharacterOffsetBegin>
            <CharacterOffsetEnd>73</CharacterOffsetEnd>
            <POS>,</POS>
          </token>
          <token id="15">
            <word>and</word>
            <lemma>and</lemma>
            <CharacterOffsetBegin>74</CharacterOffsetBegin>
            <CharacterOffsetEnd>77</CharacterOffsetEnd>
            <POS>CC</POS>
          </token>
          <token id="16">
            <word>Oslo</word>
            <lemma>Oslo</lemma>
            <CharacterOffsetBegin>78</CharacterOffsetBegin>
            <CharacterOffsetEnd>82</CharacterOffsetEnd>
            <POS>NNP</POS>
          </token>
          <token id="17">
            <word>was</word>
            <lemma>be</lemma>
            <CharacterOffsetBegin>83</CharacterOffsetBegin>
            <CharacterOffsetEnd>86</CharacterOffsetEnd>
            <POS>VBD</POS>
          </token>
          <token id="18">
            <word>the</word>
            <lemma>the</lemma>
            <CharacterOffsetBegin>87</CharacterOffsetBegin>
            <CharacterOffsetEnd>90</CharacterOffsetEnd>
            <POS>DT</POS>
          </token>
          <token id="19">
            <word>fastest</word>
            <lemma>fastest</lemma>
            <CharacterOffsetBegin>91</CharacterOffsetBegin>
            <CharacterOffsetEnd>98</CharacterOffsetEnd>
            <POS>JJS</POS>
          </token>
          <token id="20">
            <word>growing</word>
            <lemma>grow</lemma>
            <CharacterOffsetBegin>99</CharacterOffsetBegin>
            <CharacterOffsetEnd>106</CharacterOffsetEnd>
            <POS>VBG</POS>
          </token>
          <token id="21">
            <word>cargo</word>
            <lemma>cargo</lemma>
            <CharacterOffsetBegin>107</CharacterOffsetBegin>
            <CharacterOffsetEnd>112</CharacterOffsetEnd>
            <POS>NN</POS>
          </token>
          <token id="22">
            <word>airport</word>
            <lemma>airport</lemma>
            <CharacterOffsetBegin>113</CharacterOffsetBegin>
            <CharacterOffsetEnd>120</CharacterOffsetEnd>
            <POS>NN</POS>
          </token>
          <token id="23">
            <word>in</word>
            <lemma>in</lemma>
            <CharacterOffsetBegin>121</CharacterOffsetBegin>
            <CharacterOffsetEnd>123</CharacterOffsetEnd>
            <POS>IN</POS>
          </token>
          <token id="24">
            <word>Europe</word>
            <lemma>Europe</lemma>
            <CharacterOffsetBegin>124</CharacterOffsetBegin>
            <CharacterOffsetEnd>130</CharacterOffsetEnd>
            <POS>NNP</POS>
          </token>
          <token id="25">
            <word>with</word>
            <lemma>with</lemma>
            <CharacterOffsetBegin>131</CharacterOffsetBegin>
            <CharacterOffsetEnd>135</CharacterOffsetEnd>
            <POS>IN</POS>
          </token>
          <token id="26">
            <word>36</word>
            <lemma>36</lemma>
            <CharacterOffsetBegin>136</CharacterOffsetBegin>
            <CharacterOffsetEnd>138</CharacterOffsetEnd>
            <POS>CD</POS>
          </token>
          <token id="27">
            <word>per</word>
            <lemma>per</lemma>
            <CharacterOffsetBegin>139</CharacterOffsetBegin>
            <CharacterOffsetEnd>142</CharacterOffsetEnd>
            <POS>IN</POS>
          </token>
          <token id="28">
            <word>cent</word>
            <lemma>cent</lemma>
            <CharacterOffsetBegin>143</CharacterOffsetBegin>
            <CharacterOffsetEnd>147</CharacterOffsetEnd>
            <POS>NN</POS>
          </token>
          <token id="29">
            <word>.</word>
            <lemma>.</lemma>
            <CharacterOffsetBegin>147</CharacterOffsetBegin>
            <CharacterOffsetEnd>148</CharacterOffsetEnd>
            <POS>.</POS>
          </token>
        </tokens>
      </sentence>
      <sentence section="content" type="bodyText" id="4">
        <tokens>
          <token id="1">
            <word>Of</word>
            <lemma>of</lemma>
            <CharacterOffsetBegin>0</CharacterOffsetBegin>
            <CharacterOffsetEnd>2</CharacterOffsetEnd>
            <POS>IN</POS>
          </token>
          <token id="2">
            <word>the</word>
            <lemma>the</lemma>
            <CharacterOffsetBegin>3</CharacterOffsetBegin>
            <CharacterOffsetEnd>6</CharacterOffsetEnd>
            <POS>DT</POS>
          </token>
          <token id="3">
            <word>185,000</word>
            <lemma>185,000</lemma>
            <CharacterOffsetBegin>7</CharacterOffsetBegin>
            <CharacterOffsetEnd>14</CharacterOffsetEnd>
            <POS>CD</POS>
          </token>
          <token id="4">
            <word>tons</word>
            <lemma>ton</lemma>
            <CharacterOffsetBegin>15</CharacterOffsetBegin>
            <CharacterOffsetEnd>19</CharacterOffsetEnd>
            <POS>NNS</POS>
          </token>
          <token id="5">
            <word>flown</word>
            <lemma>fly</lemma>
            <CharacterOffsetBegin>20</CharacterOffsetBegin>
            <CharacterOffsetEnd>25</CharacterOffsetEnd>
            <POS>VBN</POS>
          </token>
          <token id="6">
            <word>in</word>
            <lemma>in</lemma>
            <CharacterOffsetBegin>26</CharacterOffsetBegin>
            <CharacterOffsetEnd>28</CharacterOffsetEnd>
            <POS>IN</POS>
          </token>
          <token id="7">
            <word>and</word>
            <lemma>and</lemma>
            <CharacterOffsetBegin>29</CharacterOffsetBegin>
            <CharacterOffsetEnd>32</CharacterOffsetEnd>
            <POS>CC</POS>
          </token>
          <token id="8">
            <word>out</word>
            <lemma>out</lemma>
            <CharacterOffsetBegin>33</CharacterOffsetBegin>
            <CharacterOffsetEnd>36</CharacterOffsetEnd>
            <POS>IN</POS>
          </token>
          <token id="9">
            <word>of</word>
            <lemma>of</lemma>
            <CharacterOffsetBegin>37</CharacterOffsetBegin>
            <CharacterOffsetEnd>39</CharacterOffsetEnd>
            <POS>IN</POS>
          </token>
          <token id="10">
            <word>the</word>
            <lemma>the</lemma>
            <CharacterOffsetBegin>40</CharacterOffsetBegin>
            <CharacterOffsetEnd>43</CharacterOffsetEnd>
            <POS>DT</POS>
          </token>
          <token id="11">
            <word>airport</word>
            <lemma>airport</lemma>
            <CharacterOffsetBegin>44</CharacterOffsetBegin>
            <CharacterOffsetEnd>51</CharacterOffsetEnd>
            <POS>NN</POS>
          </token>
          <token id="12">
            <word>,</word>
            <lemma>,</lemma>
            <CharacterOffsetBegin>51</CharacterOffsetBegin>
            <CharacterOffsetEnd>52</CharacterOffsetEnd>
            <POS>,</POS>
          </token>
          <token id="13">
            <word>90,000</word>
            <lemma>90,000</lemma>
            <CharacterOffsetBegin>53</CharacterOffsetBegin>
            <CharacterOffsetEnd>59</CharacterOffsetEnd>
            <POS>CD</POS>
          </token>
          <token id="14">
            <word>tons</word>
            <lemma>ton</lemma>
            <CharacterOffsetBegin>60</CharacterOffsetBegin>
            <CharacterOffsetEnd>64</CharacterOffsetEnd>
            <POS>NNS</POS>
          </token>
          <token id="15">
            <word>was</word>
            <lemma>be</lemma>
            <CharacterOffsetBegin>65</CharacterOffsetBegin>
            <CharacterOffsetEnd>68</CharacterOffsetEnd>
            <POS>VBD</POS>
          </token>
          <token id="16">
            <word>seafood</word>
            <lemma>seafood</lemma>
            <CharacterOffsetBegin>69</CharacterOffsetBegin>
            <CharacterOffsetEnd>76</CharacterOffsetEnd>
            <POS>NN</POS>
          </token>
          <token id="17">
            <word>,</word>
            <lemma>,</lemma>
            <CharacterOffsetBegin>76</CharacterOffsetBegin>
            <CharacterOffsetEnd>77</CharacterOffsetEnd>
            <POS>,</POS>
          </token>
          <token id="18">
            <word>and</word>
            <lemma>and</lemma>
            <CharacterOffsetBegin>78</CharacterOffsetBegin>
            <CharacterOffsetEnd>81</CharacterOffsetEnd>
            <POS>CC</POS>
          </token>
          <token id="19">
            <word>Norwegian</word>
            <lemma>norwegian</lemma>
            <CharacterOffsetBegin>82</CharacterOffsetBegin>
            <CharacterOffsetEnd>91</CharacterOffsetEnd>
            <POS>JJ</POS>
          </token>
          <token id="20">
            <word>seafood</word>
            <lemma>seafood</lemma>
            <CharacterOffsetBegin>92</CharacterOffsetBegin>
            <CharacterOffsetEnd>99</CharacterOffsetEnd>
            <POS>NN</POS>
          </token>
          <token id="21">
            <word>as</word>
            <lemma>as</lemma>
            <CharacterOffsetBegin>100</CharacterOffsetBegin>
            <CharacterOffsetEnd>102</CharacterOffsetEnd>
            <POS>IN</POS>
          </token>
          <token id="22">
            <word>air</word>
            <lemma>air</lemma>
            <CharacterOffsetBegin>103</CharacterOffsetBegin>
            <CharacterOffsetEnd>106</CharacterOffsetEnd>
            <POS>NN</POS>
          </token>
          <token id="23">
            <word>cargo</word>
            <lemma>cargo</lemma>
            <CharacterOffsetBegin>107</CharacterOffsetBegin>
            <CharacterOffsetEnd>112</CharacterOffsetEnd>
            <POS>NN</POS>
          </token>
          <token id="24">
            <word>is</word>
            <lemma>be</lemma>
            <CharacterOffsetBegin>113</CharacterOffsetBegin>
            <CharacterOffsetEnd>115</CharacterOffsetEnd>
            <POS>VBZ</POS>
          </token>
          <token id="25">
            <word>expected</word>
            <lemma>expect</lemma>
            <CharacterOffsetBegin>116</CharacterOffsetBegin>
            <CharacterOffsetEnd>124</CharacterOffsetEnd>
            <POS>VBN</POS>
          </token>
          <token id="26">
            <word>to</word>
            <lemma>to</lemma>
            <CharacterOffsetBegin>125</CharacterOffsetBegin>
            <CharacterOffsetEnd>127</CharacterOffsetEnd>
            <POS>TO</POS>
          </token>
          <token id="27">
            <word>reach</word>
            <lemma>reach</lemma>
            <CharacterOffsetBegin>128</CharacterOffsetBegin>
            <CharacterOffsetEnd>133</CharacterOffsetEnd>
            <POS>VB</POS>
          </token>
          <token id="28">
            <word>230,000</word>
            <lemma>230,000</lemma>
            <CharacterOffsetBegin>134</CharacterOffsetBegin>
            <CharacterOffsetEnd>141</CharacterOffsetEnd>
            <POS>CD</POS>
          </token>
          <token id="29">
            <word>tons</word>
            <lemma>ton</lemma>
            <CharacterOffsetBegin>142</CharacterOffsetBegin>
            <CharacterOffsetEnd>146</CharacterOffsetEnd>
            <POS>NNS</POS>
          </token>
          <token id="30">
            <word>in</word>
            <lemma>in</lemma>
            <CharacterOffsetBegin>147</CharacterOffsetBegin>
            <CharacterOffsetEnd>149</CharacterOffsetEnd>
            <POS>IN</POS>
          </token>
          <token id="31">
            <word>2018</word>
            <lemma>2018</lemma>
            <CharacterOffsetBegin>150</CharacterOffsetBegin>
            <CharacterOffsetEnd>154</CharacterOffsetEnd>
            <POS>CD</POS>
          </token>
          <token id="32">
            <word>.</word>
            <lemma>.</lemma>
            <CharacterOffsetBegin>154</CharacterOffsetBegin>
            <CharacterOffsetEnd>155</CharacterOffsetEnd>
            <POS>.</POS>
          </token>
        </tokens>
      </sentence>
      <sentence section="content" type="bodyText" id="5">
        <tokens>
          <token id="1">
            <word>Construction</word>
            <lemma>construction</lemma>
            <CharacterOffsetBegin>0</CharacterOffsetBegin>
            <CharacterOffsetEnd>12</CharacterOffsetEnd>
            <POS>NN</POS>
          </token>
          <token id="2">
            <word>on</word>
            <lemma>on</lemma>
            <CharacterOffsetBegin>13</CharacterOffsetBegin>
            <CharacterOffsetEnd>15</CharacterOffsetEnd>
            <POS>IN</POS>
          </token>
          <token id="3">
            <word>the</word>
            <lemma>the</lemma>
            <CharacterOffsetBegin>16</CharacterOffsetBegin>
            <CharacterOffsetEnd>19</CharacterOffsetEnd>
            <POS>DT</POS>
          </token>
          <token id="4">
            <word>terminal</word>
            <lemma>terminal</lemma>
            <CharacterOffsetBegin>20</CharacterOffsetBegin>
            <CharacterOffsetEnd>28</CharacterOffsetEnd>
            <POS>NN</POS>
          </token>
          <token id="5">
            <word>is</word>
            <lemma>be</lemma>
            <CharacterOffsetBegin>29</CharacterOffsetBegin>
            <CharacterOffsetEnd>31</CharacterOffsetEnd>
            <POS>VBZ</POS>
          </token>
          <token id="6">
            <word>expected</word>
            <lemma>expect</lemma>
            <CharacterOffsetBegin>32</CharacterOffsetBegin>
            <CharacterOffsetEnd>40</CharacterOffsetEnd>
            <POS>VBN</POS>
          </token>
          <token id="7">
            <word>to</word>
            <lemma>to</lemma>
            <CharacterOffsetBegin>41</CharacterOffsetBegin>
            <CharacterOffsetEnd>43</CharacterOffsetEnd>
            <POS>TO</POS>
          </token>
          <token id="8">
            <word>commence</word>
            <lemma>commence</lemma>
            <CharacterOffsetBegin>44</CharacterOffsetBegin>
            <CharacterOffsetEnd>52</CharacterOffsetEnd>
            <POS>VB</POS>
          </token>
          <token id="9">
            <word>in</word>
            <lemma>in</lemma>
            <CharacterOffsetBegin>53</CharacterOffsetBegin>
            <CharacterOffsetEnd>55</CharacterOffsetEnd>
            <POS>IN</POS>
          </token>
          <token id="10">
            <word>April</word>
            <lemma>April</lemma>
            <CharacterOffsetBegin>56</CharacterOffsetBegin>
            <CharacterOffsetEnd>61</CharacterOffsetEnd>
            <POS>NNP</POS>
          </token>
          <token id="11">
            <word>2019</word>
            <lemma>2019</lemma>
            <CharacterOffsetBegin>62</CharacterOffsetBegin>
            <CharacterOffsetEnd>66</CharacterOffsetEnd>
            <POS>CD</POS>
          </token>
          <token id="12">
            <word>and</word>
            <lemma>and</lemma>
            <CharacterOffsetBegin>67</CharacterOffsetBegin>
            <CharacterOffsetEnd>70</CharacterOffsetEnd>
            <POS>CC</POS>
          </token>
          <token id="13">
            <word>the</word>
            <lemma>the</lemma>
            <CharacterOffsetBegin>71</CharacterOffsetBegin>
            <CharacterOffsetEnd>74</CharacterOffsetEnd>
            <POS>DT</POS>
          </token>
          <token id="14">
            <word>opening</word>
            <lemma>opening</lemma>
            <CharacterOffsetBegin>75</CharacterOffsetBegin>
            <CharacterOffsetEnd>82</CharacterOffsetEnd>
            <POS>NN</POS>
          </token>
          <token id="15">
            <word>is</word>
            <lemma>be</lemma>
            <CharacterOffsetBegin>83</CharacterOffsetBegin>
            <CharacterOffsetEnd>85</CharacterOffsetEnd>
            <POS>VBZ</POS>
          </token>
          <token id="16">
            <word>scheduled</word>
            <lemma>schedule</lemma>
            <CharacterOffsetBegin>86</CharacterOffsetBegin>
            <CharacterOffsetEnd>95</CharacterOffsetEnd>
            <POS>VBN</POS>
          </token>
          <token id="17">
            <word>for</word>
            <lemma>for</lemma>
            <CharacterOffsetBegin>96</CharacterOffsetBegin>
            <CharacterOffsetEnd>99</CharacterOffsetEnd>
            <POS>IN</POS>
          </token>
          <token id="18">
            <word>2021</word>
            <lemma>2021</lemma>
            <CharacterOffsetBegin>100</CharacterOffsetBegin>
            <CharacterOffsetEnd>104</CharacterOffsetEnd>
            <POS>CD</POS>
          </token>
          <token id="19">
            <word>.</word>
            <lemma>.</lemma>
            <CharacterOffsetBegin>104</CharacterOffsetBegin>
            <CharacterOffsetEnd>105</CharacterOffsetEnd>
            <POS>.</POS>
          </token>
        </tokens>
      </sentence>
      <sentence section="content" type="bodyText" id="6">
        <tokens>
          <token id="1">
            <word>Avinor</word>
            <lemma>Avinor</lemma>
            <CharacterOffsetBegin>0</CharacterOffsetBegin>
            <CharacterOffsetEnd>6</CharacterOffsetEnd>
            <POS>NNP</POS>
          </token>
          <token id="2">
            <word>Oslo</word>
            <lemma>Oslo</lemma>
            <CharacterOffsetBegin>7</CharacterOffsetBegin>
            <CharacterOffsetEnd>11</CharacterOffsetEnd>
            <POS>NNP</POS>
          </token>
          <token id="3">
            <word>Airport</word>
            <lemma>Airport</lemma>
            <CharacterOffsetBegin>12</CharacterOffsetBegin>
            <CharacterOffsetEnd>19</CharacterOffsetEnd>
            <POS>NNP</POS>
          </token>
          <token id="4">
            <word>director</word>
            <lemma>director</lemma>
            <CharacterOffsetBegin>20</CharacterOffsetBegin>
            <CharacterOffsetEnd>28</CharacterOffsetEnd>
            <POS>NN</POS>
          </token>
          <token id="5">
            <word>of</word>
            <lemma>of</lemma>
            <CharacterOffsetBegin>29</CharacterOffsetBegin>
            <CharacterOffsetEnd>31</CharacterOffsetEnd>
            <POS>IN</POS>
          </token>
          <token id="6">
            <word>cargo</word>
            <lemma>cargo</lemma>
            <CharacterOffsetBegin>32</CharacterOffsetBegin>
            <CharacterOffsetEnd>37</CharacterOffsetEnd>
            <POS>NN</POS>
          </token>
          <token id="7">
            <word>,</word>
            <lemma>,</lemma>
            <CharacterOffsetBegin>37</CharacterOffsetBegin>
            <CharacterOffsetEnd>38</CharacterOffsetEnd>
            <POS>,</POS>
          </token>
          <token id="8">
            <word>Martin</word>
            <lemma>Martin</lemma>
            <CharacterOffsetBegin>39</CharacterOffsetBegin>
            <CharacterOffsetEnd>45</CharacterOffsetEnd>
            <POS>NNP</POS>
          </token>
          <token id="9">
            <word>Langaas</word>
            <lemma>Langaas</lemma>
            <CharacterOffsetBegin>46</CharacterOffsetBegin>
            <CharacterOffsetEnd>53</CharacterOffsetEnd>
            <POS>NNP</POS>
          </token>
          <token id="10">
            <word>says</word>
            <lemma>say</lemma>
            <CharacterOffsetBegin>54</CharacterOffsetBegin>
            <CharacterOffsetEnd>58</CharacterOffsetEnd>
            <POS>VBZ</POS>
          </token>
          <token id="11">
            <word>:</word>
            <lemma>:</lemma>
            <CharacterOffsetBegin>58</CharacterOffsetBegin>
            <CharacterOffsetEnd>59</CharacterOffsetEnd>
            <POS>:</POS>
          </token>
          <token id="12">
            <word>``</word>
            <lemma>``</lemma>
            <CharacterOffsetBegin>60</CharacterOffsetBegin>
            <CharacterOffsetEnd>61</CharacterOffsetEnd>
            <POS>``</POS>
          </token>
          <token id="13">
            <word>This</word>
            <lemma>this</lemma>
            <CharacterOffsetBegin>61</CharacterOffsetBegin>
            <CharacterOffsetEnd>65</CharacterOffsetEnd>
            <POS>DT</POS>
          </token>
          <token id="14">
            <word>is</word>
            <lemma>be</lemma>
            <CharacterOffsetBegin>66</CharacterOffsetBegin>
            <CharacterOffsetEnd>68</CharacterOffsetEnd>
            <POS>VBZ</POS>
          </token>
          <token id="15">
            <word>a</word>
            <lemma>a</lemma>
            <CharacterOffsetBegin>69</CharacterOffsetBegin>
            <CharacterOffsetEnd>70</CharacterOffsetEnd>
            <POS>DT</POS>
          </token>
          <token id="16">
            <word>unique</word>
            <lemma>unique</lemma>
            <CharacterOffsetBegin>71</CharacterOffsetBegin>
            <CharacterOffsetEnd>77</CharacterOffsetEnd>
            <POS>JJ</POS>
          </token>
          <token id="17">
            <word>opportunity</word>
            <lemma>opportunity</lemma>
            <CharacterOffsetBegin>78</CharacterOffsetBegin>
            <CharacterOffsetEnd>89</CharacterOffsetEnd>
            <POS>NN</POS>
          </token>
          <token id="18">
            <word>to</word>
            <lemma>to</lemma>
            <CharacterOffsetBegin>90</CharacterOffsetBegin>
            <CharacterOffsetEnd>92</CharacterOffsetEnd>
            <POS>TO</POS>
          </token>
          <token id="19">
            <word>define</word>
            <lemma>define</lemma>
            <CharacterOffsetBegin>93</CharacterOffsetBegin>
            <CharacterOffsetEnd>99</CharacterOffsetEnd>
            <POS>VB</POS>
          </token>
          <token id="20">
            <word>the</word>
            <lemma>the</lemma>
            <CharacterOffsetBegin>100</CharacterOffsetBegin>
            <CharacterOffsetEnd>103</CharacterOffsetEnd>
            <POS>DT</POS>
          </token>
          <token id="21">
            <word>future</word>
            <lemma>future</lemma>
            <CharacterOffsetBegin>104</CharacterOffsetBegin>
            <CharacterOffsetEnd>110</CharacterOffsetEnd>
            <POS>NN</POS>
          </token>
          <token id="22">
            <word>of</word>
            <lemma>of</lemma>
            <CharacterOffsetBegin>111</CharacterOffsetBegin>
            <CharacterOffsetEnd>113</CharacterOffsetEnd>
            <POS>IN</POS>
          </token>
          <token id="23">
            <word>cool</word>
            <lemma>cool</lemma>
            <CharacterOffsetBegin>114</CharacterOffsetBegin>
            <CharacterOffsetEnd>118</CharacterOffsetEnd>
            <POS>JJ</POS>
          </token>
          <token id="24">
            <word>chain</word>
            <lemma>chain</lemma>
            <CharacterOffsetBegin>119</CharacterOffsetBegin>
            <CharacterOffsetEnd>124</CharacterOffsetEnd>
            <POS>NN</POS>
          </token>
          <token id="25">
            <word>logistics</word>
            <lemma>logistics</lemma>
            <CharacterOffsetBegin>125</CharacterOffsetBegin>
            <CharacterOffsetEnd>134</CharacterOffsetEnd>
            <POS>NNS</POS>
          </token>
          <token id="26">
            <word>for</word>
            <lemma>for</lemma>
            <CharacterOffsetBegin>135</CharacterOffsetBegin>
            <CharacterOffsetEnd>138</CharacterOffsetEnd>
            <POS>IN</POS>
          </token>
          <token id="27">
            <word>seafood</word>
            <lemma>seafood</lemma>
            <CharacterOffsetBegin>139</CharacterOffsetBegin>
            <CharacterOffsetEnd>146</CharacterOffsetEnd>
            <POS>NN</POS>
          </token>
          <token id="28">
            <word>as</word>
            <lemma>as</lemma>
            <CharacterOffsetBegin>147</CharacterOffsetBegin>
            <CharacterOffsetEnd>149</CharacterOffsetEnd>
            <POS>IN</POS>
          </token>
          <token id="29">
            <word>air</word>
            <lemma>air</lemma>
            <CharacterOffsetBegin>150</CharacterOffsetBegin>
            <CharacterOffsetEnd>153</CharacterOffsetEnd>
            <POS>NN</POS>
          </token>
          <token id="30">
            <word>cargo</word>
            <lemma>cargo</lemma>
            <CharacterOffsetBegin>154</CharacterOffsetBegin>
            <CharacterOffsetEnd>159</CharacterOffsetEnd>
            <POS>NN</POS>
          </token>
          <token id="31">
            <word>.</word>
            <lemma>.</lemma>
            <CharacterOffsetBegin>159</CharacterOffsetBegin>
            <CharacterOffsetEnd>160</CharacterOffsetEnd>
            <POS>.</POS>
          </token>
        </tokens>
      </sentence>
      <sentence section="content" type="bodyText" id="7">
        <tokens>
          <token id="1">
            <word>The</word>
            <lemma>the</lemma>
            <CharacterOffsetBegin>161</CharacterOffsetBegin>
            <CharacterOffsetEnd>164</CharacterOffsetEnd>
            <POS>DT</POS>
          </token>
          <token id="2">
            <word>Seafood</word>
            <lemma>Seafood</lemma>
            <CharacterOffsetBegin>165</CharacterOffsetBegin>
            <CharacterOffsetEnd>172</CharacterOffsetEnd>
            <POS>NNP</POS>
          </token>
          <token id="3">
            <word>Centre</word>
            <lemma>Centre</lemma>
            <CharacterOffsetBegin>173</CharacterOffsetBegin>
            <CharacterOffsetEnd>179</CharacterOffsetEnd>
            <POS>NNP</POS>
          </token>
          <token id="4">
            <word>at</word>
            <lemma>at</lemma>
            <CharacterOffsetBegin>180</CharacterOffsetBegin>
            <CharacterOffsetEnd>182</CharacterOffsetEnd>
            <POS>IN</POS>
          </token>
          <token id="5">
            <word>Oslo</word>
            <lemma>Oslo</lemma>
            <CharacterOffsetBegin>183</CharacterOffsetBegin>
            <CharacterOffsetEnd>187</CharacterOffsetEnd>
            <POS>NNP</POS>
          </token>
          <token id="6">
            <word>Airport</word>
            <lemma>Airport</lemma>
            <CharacterOffsetBegin>188</CharacterOffsetBegin>
            <CharacterOffsetEnd>195</CharacterOffsetEnd>
            <POS>NNP</POS>
          </token>
          <token id="7">
            <word>will</word>
            <lemma>will</lemma>
            <CharacterOffsetBegin>196</CharacterOffsetBegin>
            <CharacterOffsetEnd>200</CharacterOffsetEnd>
            <POS>MD</POS>
          </token>
          <token id="8">
            <word>increase</word>
            <lemma>increase</lemma>
            <CharacterOffsetBegin>201</CharacterOffsetBegin>
            <CharacterOffsetEnd>209</CharacterOffsetEnd>
            <POS>VB</POS>
          </token>
          <token id="9">
            <word>the</word>
            <lemma>the</lemma>
            <CharacterOffsetBegin>210</CharacterOffsetBegin>
            <CharacterOffsetEnd>213</CharacterOffsetEnd>
            <POS>DT</POS>
          </token>
          <token id="10">
            <word>competitiveness</word>
            <lemma>competitiveness</lemma>
            <CharacterOffsetBegin>214</CharacterOffsetBegin>
            <CharacterOffsetEnd>229</CharacterOffsetEnd>
            <POS>NN</POS>
          </token>
          <token id="11">
            <word>of</word>
            <lemma>of</lemma>
            <CharacterOffsetBegin>230</CharacterOffsetBegin>
            <CharacterOffsetEnd>232</CharacterOffsetEnd>
            <POS>IN</POS>
          </token>
          <token id="12">
            <word>Norwegian</word>
            <lemma>norwegian</lemma>
            <CharacterOffsetBegin>233</CharacterOffsetBegin>
            <CharacterOffsetEnd>242</CharacterOffsetEnd>
            <POS>JJ</POS>
          </token>
          <token id="13">
            <word>Seafood</word>
            <lemma>seafood</lemma>
            <CharacterOffsetBegin>243</CharacterOffsetBegin>
            <CharacterOffsetEnd>250</CharacterOffsetEnd>
            <POS>NN</POS>
          </token>
          <token id="14">
            <word>globally</word>
            <lemma>globally</lemma>
            <CharacterOffsetBegin>251</CharacterOffsetBegin>
            <CharacterOffsetEnd>259</CharacterOffsetEnd>
            <POS>RB</POS>
          </token>
          <token id="15">
            <word>and</word>
            <lemma>and</lemma>
            <CharacterOffsetBegin>260</CharacterOffsetBegin>
            <CharacterOffsetEnd>263</CharacterOffsetEnd>
            <POS>CC</POS>
          </token>
          <token id="16">
            <word>industrialise</word>
            <lemma>industrialise</lemma>
            <CharacterOffsetBegin>264</CharacterOffsetBegin>
            <CharacterOffsetEnd>277</CharacterOffsetEnd>
            <POS>VB</POS>
          </token>
          <token id="17">
            <word>the</word>
            <lemma>the</lemma>
            <CharacterOffsetBegin>278</CharacterOffsetBegin>
            <CharacterOffsetEnd>281</CharacterOffsetEnd>
            <POS>DT</POS>
          </token>
          <token id="18">
            <word>handling</word>
            <lemma>handling</lemma>
            <CharacterOffsetBegin>282</CharacterOffsetBegin>
            <CharacterOffsetEnd>290</CharacterOffsetEnd>
            <POS>NN</POS>
          </token>
          <token id="19">
            <word>.</word>
            <lemma>.</lemma>
            <CharacterOffsetBegin>290</CharacterOffsetBegin>
            <CharacterOffsetEnd>291</CharacterOffsetEnd>
            <POS>.</POS>
          </token>
        </tokens>
      </sentence>
      <sentence section="content" type="bodyText" id="8">
        <tokens>
          <token id="1">
            <word>``</word>
            <lemma>``</lemma>
            <CharacterOffsetBegin>0</CharacterOffsetBegin>
            <CharacterOffsetEnd>1</CharacterOffsetEnd>
            <POS>``</POS>
          </token>
          <token id="2">
            <word>With</word>
            <lemma>with</lemma>
            <CharacterOffsetBegin>1</CharacterOffsetBegin>
            <CharacterOffsetEnd>5</CharacterOffsetEnd>
            <POS>IN</POS>
          </token>
          <token id="3">
            <word>an</word>
            <lemma>a</lemma>
            <CharacterOffsetBegin>6</CharacterOffsetBegin>
            <CharacterOffsetEnd>8</CharacterOffsetEnd>
            <POS>DT</POS>
          </token>
          <token id="4">
            <word>experienced</word>
            <lemma>experienced</lemma>
            <CharacterOffsetBegin>9</CharacterOffsetBegin>
            <CharacterOffsetEnd>20</CharacterOffsetEnd>
            <POS>JJ</POS>
          </token>
          <token id="5">
            <word>international</word>
            <lemma>international</lemma>
            <CharacterOffsetBegin>21</CharacterOffsetBegin>
            <CharacterOffsetEnd>34</CharacterOffsetEnd>
            <POS>JJ</POS>
          </token>
          <token id="6">
            <word>handler</word>
            <lemma>handler</lemma>
            <CharacterOffsetBegin>35</CharacterOffsetBegin>
            <CharacterOffsetEnd>42</CharacterOffsetEnd>
            <POS>NN</POS>
          </token>
          <token id="7">
            <word>as</word>
            <lemma>as</lemma>
            <CharacterOffsetBegin>43</CharacterOffsetBegin>
            <CharacterOffsetEnd>45</CharacterOffsetEnd>
            <POS>IN</POS>
          </token>
          <token id="8">
            <word>WFS</word>
            <lemma>WFS</lemma>
            <CharacterOffsetBegin>46</CharacterOffsetBegin>
            <CharacterOffsetEnd>49</CharacterOffsetEnd>
            <POS>NNP</POS>
          </token>
          <token id="9">
            <word>,</word>
            <lemma>,</lemma>
            <CharacterOffsetBegin>49</CharacterOffsetBegin>
            <CharacterOffsetEnd>50</CharacterOffsetEnd>
            <POS>,</POS>
          </token>
          <token id="10">
            <word>we</word>
            <lemma>we</lemma>
            <CharacterOffsetBegin>51</CharacterOffsetBegin>
            <CharacterOffsetEnd>53</CharacterOffsetEnd>
            <POS>PRP</POS>
          </token>
          <token id="11">
            <word>believe</word>
            <lemma>believe</lemma>
            <CharacterOffsetBegin>54</CharacterOffsetBegin>
            <CharacterOffsetEnd>61</CharacterOffsetEnd>
            <POS>VBP</POS>
          </token>
          <token id="12">
            <word>Oslo</word>
            <lemma>Oslo</lemma>
            <CharacterOffsetBegin>62</CharacterOffsetBegin>
            <CharacterOffsetEnd>66</CharacterOffsetEnd>
            <POS>NNP</POS>
          </token>
          <token id="13">
            <word>Airport</word>
            <lemma>Airport</lemma>
            <CharacterOffsetBegin>67</CharacterOffsetBegin>
            <CharacterOffsetEnd>74</CharacterOffsetEnd>
            <POS>NNP</POS>
          </token>
          <token id="14">
            <word>will</word>
            <lemma>will</lemma>
            <CharacterOffsetBegin>75</CharacterOffsetBegin>
            <CharacterOffsetEnd>79</CharacterOffsetEnd>
            <POS>MD</POS>
          </token>
          <token id="15">
            <word>increase</word>
            <lemma>increase</lemma>
            <CharacterOffsetBegin>80</CharacterOffsetBegin>
            <CharacterOffsetEnd>88</CharacterOffsetEnd>
            <POS>VB</POS>
          </token>
          <token id="16">
            <word>its</word>
            <lemma>its</lemma>
            <CharacterOffsetBegin>89</CharacterOffsetBegin>
            <CharacterOffsetEnd>92</CharacterOffsetEnd>
            <POS>PRP$</POS>
          </token>
          <token id="17">
            <word>competitive</word>
            <lemma>competitive</lemma>
            <CharacterOffsetBegin>93</CharacterOffsetBegin>
            <CharacterOffsetEnd>104</CharacterOffsetEnd>
            <POS>JJ</POS>
          </token>
          <token id="18">
            <word>advantage</word>
            <lemma>advantage</lemma>
            <CharacterOffsetBegin>105</CharacterOffsetBegin>
            <CharacterOffsetEnd>114</CharacterOffsetEnd>
            <POS>NN</POS>
          </token>
          <token id="19">
            <word>as</word>
            <lemma>as</lemma>
            <CharacterOffsetBegin>115</CharacterOffsetBegin>
            <CharacterOffsetEnd>117</CharacterOffsetEnd>
            <POS>IN</POS>
          </token>
          <token id="20">
            <word>the</word>
            <lemma>the</lemma>
            <CharacterOffsetBegin>118</CharacterOffsetBegin>
            <CharacterOffsetEnd>121</CharacterOffsetEnd>
            <POS>DT</POS>
          </token>
          <token id="21">
            <word>preferred</word>
            <lemma>preferred</lemma>
            <CharacterOffsetBegin>122</CharacterOffsetBegin>
            <CharacterOffsetEnd>131</CharacterOffsetEnd>
            <POS>JJ</POS>
          </token>
          <token id="22">
            <word>cargo</word>
            <lemma>cargo</lemma>
            <CharacterOffsetBegin>132</CharacterOffsetBegin>
            <CharacterOffsetEnd>137</CharacterOffsetEnd>
            <POS>NN</POS>
          </token>
          <token id="23">
            <word>hub</word>
            <lemma>hub</lemma>
            <CharacterOffsetBegin>138</CharacterOffsetBegin>
            <CharacterOffsetEnd>141</CharacterOffsetEnd>
            <POS>NN</POS>
          </token>
          <token id="24">
            <word>in</word>
            <lemma>in</lemma>
            <CharacterOffsetBegin>142</CharacterOffsetBegin>
            <CharacterOffsetEnd>144</CharacterOffsetEnd>
            <POS>IN</POS>
          </token>
          <token id="25">
            <word>Northern</word>
            <lemma>Northern</lemma>
            <CharacterOffsetBegin>145</CharacterOffsetBegin>
            <CharacterOffsetEnd>153</CharacterOffsetEnd>
            <POS>NNP</POS>
          </token>
          <token id="26">
            <word>Europe</word>
            <lemma>Europe</lemma>
            <CharacterOffsetBegin>154</CharacterOffsetBegin>
            <CharacterOffsetEnd>160</CharacterOffsetEnd>
            <POS>NNP</POS>
          </token>
          <token id="27">
            <word>.</word>
            <lemma>.</lemma>
            <CharacterOffsetBegin>160</CharacterOffsetBegin>
            <CharacterOffsetEnd>161</CharacterOffsetEnd>
            <POS>.</POS>
          </token>
          <token id="28">
            <word>''</word>
            <lemma>''</lemma>
            <CharacterOffsetBegin>161</CharacterOffsetBegin>
            <CharacterOffsetEnd>162</CharacterOffsetEnd>
            <POS>''</POS>
          </token>
        </tokens>
      </sentence>
      <sentence section="content" type="bodyText" id="9">
        <tokens>
          <token id="1">
            <word>Oslo</word>
            <lemma>Oslo</lemma>
            <CharacterOffsetBegin>0</CharacterOffsetBegin>
            <CharacterOffsetEnd>4</CharacterOffsetEnd>
            <POS>NNP</POS>
          </token>
          <token id="2">
            <word>Airport</word>
            <lemma>Airport</lemma>
            <CharacterOffsetBegin>5</CharacterOffsetBegin>
            <CharacterOffsetEnd>12</CharacterOffsetEnd>
            <POS>NNP</POS>
          </token>
          <token id="3">
            <word>executive</word>
            <lemma>executive</lemma>
            <CharacterOffsetBegin>13</CharacterOffsetBegin>
            <CharacterOffsetEnd>22</CharacterOffsetEnd>
            <POS>NN</POS>
          </token>
          <token id="4">
            <word>vice</word>
            <lemma>vice</lemma>
            <CharacterOffsetBegin>23</CharacterOffsetBegin>
            <CharacterOffsetEnd>27</CharacterOffsetEnd>
            <POS>NN</POS>
          </token>
          <token id="5">
            <word>president</word>
            <lemma>president</lemma>
            <CharacterOffsetBegin>28</CharacterOffsetBegin>
            <CharacterOffsetEnd>37</CharacterOffsetEnd>
            <POS>NN</POS>
          </token>
          <token id="6">
            <word>,</word>
            <lemma>,</lemma>
            <CharacterOffsetBegin>37</CharacterOffsetBegin>
            <CharacterOffsetEnd>38</CharacterOffsetEnd>
            <POS>,</POS>
          </token>
          <token id="7">
            <word>Øyvind</word>
            <lemma>Øyvind</lemma>
            <CharacterOffsetBegin>39</CharacterOffsetBegin>
            <CharacterOffsetEnd>45</CharacterOffsetEnd>
            <POS>NNP</POS>
          </token>
          <token id="8">
            <word>Hasaas</word>
            <lemma>Hasaas</lemma>
            <CharacterOffsetBegin>46</CharacterOffsetBegin>
            <CharacterOffsetEnd>52</CharacterOffsetEnd>
            <POS>NNP</POS>
          </token>
          <token id="9">
            <word>adds</word>
            <lemma>add</lemma>
            <CharacterOffsetBegin>53</CharacterOffsetBegin>
            <CharacterOffsetEnd>57</CharacterOffsetEnd>
            <POS>VBZ</POS>
          </token>
          <token id="10">
            <word>:</word>
            <lemma>:</lemma>
            <CharacterOffsetBegin>57</CharacterOffsetBegin>
            <CharacterOffsetEnd>58</CharacterOffsetEnd>
            <POS>:</POS>
          </token>
          <token id="11">
            <word>``</word>
            <lemma>``</lemma>
            <CharacterOffsetBegin>59</CharacterOffsetBegin>
            <CharacterOffsetEnd>60</CharacterOffsetEnd>
            <POS>``</POS>
          </token>
          <token id="12">
            <word>We</word>
            <lemma>we</lemma>
            <CharacterOffsetBegin>60</CharacterOffsetBegin>
            <CharacterOffsetEnd>62</CharacterOffsetEnd>
            <POS>PRP</POS>
          </token>
          <token id="13">
            <word>have</word>
            <lemma>have</lemma>
            <CharacterOffsetBegin>63</CharacterOffsetBegin>
            <CharacterOffsetEnd>67</CharacterOffsetEnd>
            <POS>VBP</POS>
          </token>
          <token id="14">
            <word>listened</word>
            <lemma>listen</lemma>
            <CharacterOffsetBegin>68</CharacterOffsetBegin>
            <CharacterOffsetEnd>76</CharacterOffsetEnd>
            <POS>VBN</POS>
          </token>
          <token id="15">
            <word>to</word>
            <lemma>to</lemma>
            <CharacterOffsetBegin>77</CharacterOffsetBegin>
            <CharacterOffsetEnd>79</CharacterOffsetEnd>
            <POS>TO</POS>
          </token>
          <token id="16">
            <word>the</word>
            <lemma>the</lemma>
            <CharacterOffsetBegin>80</CharacterOffsetBegin>
            <CharacterOffsetEnd>83</CharacterOffsetEnd>
            <POS>DT</POS>
          </token>
          <token id="17">
            <word>exporters</word>
            <lemma>exporter</lemma>
            <CharacterOffsetBegin>84</CharacterOffsetBegin>
            <CharacterOffsetEnd>93</CharacterOffsetEnd>
            <POS>NNS</POS>
          </token>
          <token id="18">
            <word>and</word>
            <lemma>and</lemma>
            <CharacterOffsetBegin>94</CharacterOffsetBegin>
            <CharacterOffsetEnd>97</CharacterOffsetEnd>
            <POS>CC</POS>
          </token>
          <token id="19">
            <word>their</word>
            <lemma>they</lemma>
            <CharacterOffsetBegin>98</CharacterOffsetBegin>
            <CharacterOffsetEnd>103</CharacterOffsetEnd>
            <POS>PRP$</POS>
          </token>
          <token id="20">
            <word>needs</word>
            <lemma>need</lemma>
            <CharacterOffsetBegin>104</CharacterOffsetBegin>
            <CharacterOffsetEnd>109</CharacterOffsetEnd>
            <POS>NNS</POS>
          </token>
          <token id="21">
            <word>to</word>
            <lemma>to</lemma>
            <CharacterOffsetBegin>110</CharacterOffsetBegin>
            <CharacterOffsetEnd>112</CharacterOffsetEnd>
            <POS>TO</POS>
          </token>
          <token id="22">
            <word>ensure</word>
            <lemma>ensure</lemma>
            <CharacterOffsetBegin>113</CharacterOffsetBegin>
            <CharacterOffsetEnd>119</CharacterOffsetEnd>
            <POS>VB</POS>
          </token>
          <token id="23">
            <word>quality</word>
            <lemma>quality</lemma>
            <CharacterOffsetBegin>120</CharacterOffsetBegin>
            <CharacterOffsetEnd>127</CharacterOffsetEnd>
            <POS>NN</POS>
          </token>
          <token id="24">
            <word>and</word>
            <lemma>and</lemma>
            <CharacterOffsetBegin>128</CharacterOffsetBegin>
            <CharacterOffsetEnd>131</CharacterOffsetEnd>
            <POS>CC</POS>
          </token>
          <token id="25">
            <word>time</word>
            <lemma>time</lemma>
            <CharacterOffsetBegin>132</CharacterOffsetBegin>
            <CharacterOffsetEnd>136</CharacterOffsetEnd>
            <POS>NN</POS>
          </token>
          <token id="26">
            <word>to</word>
            <lemma>to</lemma>
            <CharacterOffsetBegin>137</CharacterOffsetBegin>
            <CharacterOffsetEnd>139</CharacterOffsetEnd>
            <POS>TO</POS>
          </token>
          <token id="27">
            <word>market</word>
            <lemma>market</lemma>
            <CharacterOffsetBegin>140</CharacterOffsetBegin>
            <CharacterOffsetEnd>146</CharacterOffsetEnd>
            <POS>NN</POS>
          </token>
          <token id="28">
            <word>.</word>
            <lemma>.</lemma>
            <CharacterOffsetBegin>146</CharacterOffsetBegin>
            <CharacterOffsetEnd>147</CharacterOffsetEnd>
            <POS>.</POS>
          </token>
        </tokens>
      </sentence>
      <sentence section="content" type="bodyText" id="10">
        <tokens>
          <token id="1">
            <word>I</word>
            <lemma>I</lemma>
            <CharacterOffsetBegin>148</CharacterOffsetBegin>
            <CharacterOffsetEnd>149</CharacterOffsetEnd>
            <POS>PRP</POS>
          </token>
          <token id="2">
            <word>believe</word>
            <lemma>believe</lemma>
            <CharacterOffsetBegin>150</CharacterOffsetBegin>
            <CharacterOffsetEnd>157</CharacterOffsetEnd>
            <POS>VBP</POS>
          </token>
          <token id="3">
            <word>the</word>
            <lemma>the</lemma>
            <CharacterOffsetBegin>158</CharacterOffsetBegin>
            <CharacterOffsetEnd>161</CharacterOffsetEnd>
            <POS>DT</POS>
          </token>
          <token id="4">
            <word>dedication</word>
            <lemma>dedication</lemma>
            <CharacterOffsetBegin>162</CharacterOffsetBegin>
            <CharacterOffsetEnd>172</CharacterOffsetEnd>
            <POS>NN</POS>
          </token>
          <token id="5">
            <word>from</word>
            <lemma>from</lemma>
            <CharacterOffsetBegin>173</CharacterOffsetBegin>
            <CharacterOffsetEnd>177</CharacterOffsetEnd>
            <POS>IN</POS>
          </token>
          <token id="6">
            <word>the</word>
            <lemma>the</lemma>
            <CharacterOffsetBegin>178</CharacterOffsetBegin>
            <CharacterOffsetEnd>181</CharacterOffsetEnd>
            <POS>DT</POS>
          </token>
          <token id="7">
            <word>Seafood</word>
            <lemma>Seafood</lemma>
            <CharacterOffsetBegin>182</CharacterOffsetBegin>
            <CharacterOffsetEnd>189</CharacterOffsetEnd>
            <POS>NNP</POS>
          </token>
          <token id="8">
            <word>Exporters</word>
            <lemma>exporter</lemma>
            <CharacterOffsetBegin>190</CharacterOffsetBegin>
            <CharacterOffsetEnd>199</CharacterOffsetEnd>
            <POS>NNS</POS>
          </token>
          <token id="9">
            <word>in</word>
            <lemma>in</lemma>
            <CharacterOffsetBegin>200</CharacterOffsetBegin>
            <CharacterOffsetEnd>202</CharacterOffsetEnd>
            <POS>IN</POS>
          </token>
          <token id="10">
            <word>this</word>
            <lemma>this</lemma>
            <CharacterOffsetBegin>203</CharacterOffsetBegin>
            <CharacterOffsetEnd>207</CharacterOffsetEnd>
            <POS>DT</POS>
          </token>
          <token id="11">
            <word>project</word>
            <lemma>project</lemma>
            <CharacterOffsetBegin>208</CharacterOffsetBegin>
            <CharacterOffsetEnd>215</CharacterOffsetEnd>
            <POS>NN</POS>
          </token>
          <token id="12">
            <word>is</word>
            <lemma>be</lemma>
            <CharacterOffsetBegin>216</CharacterOffsetBegin>
            <CharacterOffsetEnd>218</CharacterOffsetEnd>
            <POS>VBZ</POS>
          </token>
          <token id="13">
            <word>an</word>
            <lemma>a</lemma>
            <CharacterOffsetBegin>219</CharacterOffsetBegin>
            <CharacterOffsetEnd>221</CharacterOffsetEnd>
            <POS>DT</POS>
          </token>
          <token id="14">
            <word>acknowledgement</word>
            <lemma>acknowledgement</lemma>
            <CharacterOffsetBegin>222</CharacterOffsetBegin>
            <CharacterOffsetEnd>237</CharacterOffsetEnd>
            <POS>NN</POS>
          </token>
          <token id="15">
            <word>of</word>
            <lemma>of</lemma>
            <CharacterOffsetBegin>238</CharacterOffsetBegin>
            <CharacterOffsetEnd>240</CharacterOffsetEnd>
            <POS>IN</POS>
          </token>
          <token id="16">
            <word>the</word>
            <lemma>the</lemma>
            <CharacterOffsetBegin>241</CharacterOffsetBegin>
            <CharacterOffsetEnd>244</CharacterOffsetEnd>
            <POS>DT</POS>
          </token>
          <token id="17">
            <word>project</word>
            <lemma>project</lemma>
            <CharacterOffsetBegin>245</CharacterOffsetBegin>
            <CharacterOffsetEnd>252</CharacterOffsetEnd>
            <POS>NN</POS>
          </token>
          <token id="18">
            <word>itself</word>
            <lemma>itself</lemma>
            <CharacterOffsetBegin>253</CharacterOffsetBegin>
            <CharacterOffsetEnd>259</CharacterOffsetEnd>
            <POS>PRP</POS>
          </token>
          <token id="19">
            <word>.</word>
            <lemma>.</lemma>
            <CharacterOffsetBegin>259</CharacterOffsetBegin>
            <CharacterOffsetEnd>260</CharacterOffsetEnd>
            <POS>.</POS>
          </token>
        </tokens>
      </sentence>
      <sentence section="content" type="bodyText" id="11">
        <tokens>
          <token id="1">
            <word>``</word>
            <lemma>``</lemma>
            <CharacterOffsetBegin>0</CharacterOffsetBegin>
            <CharacterOffsetEnd>1</CharacterOffsetEnd>
            <POS>``</POS>
          </token>
          <token id="2">
            <word>The</word>
            <lemma>the</lemma>
            <CharacterOffsetBegin>1</CharacterOffsetBegin>
            <CharacterOffsetEnd>4</CharacterOffsetEnd>
            <POS>DT</POS>
          </token>
          <token id="3">
            <word>Seafood</word>
            <lemma>Seafood</lemma>
            <CharacterOffsetBegin>5</CharacterOffsetBegin>
            <CharacterOffsetEnd>12</CharacterOffsetEnd>
            <POS>NNP</POS>
          </token>
          <token id="4">
            <word>Centre</word>
            <lemma>Centre</lemma>
            <CharacterOffsetBegin>13</CharacterOffsetBegin>
            <CharacterOffsetEnd>19</CharacterOffsetEnd>
            <POS>NNP</POS>
          </token>
          <token id="5">
            <word>will</word>
            <lemma>will</lemma>
            <CharacterOffsetBegin>20</CharacterOffsetBegin>
            <CharacterOffsetEnd>24</CharacterOffsetEnd>
            <POS>MD</POS>
          </token>
          <token id="6">
            <word>create</word>
            <lemma>create</lemma>
            <CharacterOffsetBegin>25</CharacterOffsetBegin>
            <CharacterOffsetEnd>31</CharacterOffsetEnd>
            <POS>VB</POS>
          </token>
          <token id="7">
            <word>value</word>
            <lemma>value</lemma>
            <CharacterOffsetBegin>32</CharacterOffsetBegin>
            <CharacterOffsetEnd>37</CharacterOffsetEnd>
            <POS>NN</POS>
          </token>
          <token id="8">
            <word>for</word>
            <lemma>for</lemma>
            <CharacterOffsetBegin>38</CharacterOffsetBegin>
            <CharacterOffsetEnd>41</CharacterOffsetEnd>
            <POS>IN</POS>
          </token>
          <token id="9">
            <word>all</word>
            <lemma>all</lemma>
            <CharacterOffsetBegin>42</CharacterOffsetBegin>
            <CharacterOffsetEnd>45</CharacterOffsetEnd>
            <POS>DT</POS>
          </token>
          <token id="10">
            <word>of</word>
            <lemma>of</lemma>
            <CharacterOffsetBegin>46</CharacterOffsetBegin>
            <CharacterOffsetEnd>48</CharacterOffsetEnd>
            <POS>IN</POS>
          </token>
          <token id="11">
            <word>Norway</word>
            <lemma>Norway</lemma>
            <CharacterOffsetBegin>49</CharacterOffsetBegin>
            <CharacterOffsetEnd>55</CharacterOffsetEnd>
            <POS>NNP</POS>
          </token>
          <token id="12">
            <word>and</word>
            <lemma>and</lemma>
            <CharacterOffsetBegin>56</CharacterOffsetBegin>
            <CharacterOffsetEnd>59</CharacterOffsetEnd>
            <POS>CC</POS>
          </token>
          <token id="13">
            <word>increase</word>
            <lemma>increase</lemma>
            <CharacterOffsetBegin>60</CharacterOffsetBegin>
            <CharacterOffsetEnd>68</CharacterOffsetEnd>
            <POS>VB</POS>
          </token>
          <token id="14">
            <word>the</word>
            <lemma>the</lemma>
            <CharacterOffsetBegin>69</CharacterOffsetBegin>
            <CharacterOffsetEnd>72</CharacterOffsetEnd>
            <POS>DT</POS>
          </token>
          <token id="15">
            <word>competitiveness</word>
            <lemma>competitiveness</lemma>
            <CharacterOffsetBegin>73</CharacterOffsetBegin>
            <CharacterOffsetEnd>88</CharacterOffsetEnd>
            <POS>NN</POS>
          </token>
          <token id="16">
            <word>of</word>
            <lemma>of</lemma>
            <CharacterOffsetBegin>89</CharacterOffsetBegin>
            <CharacterOffsetEnd>91</CharacterOffsetEnd>
            <POS>IN</POS>
          </token>
          <token id="17">
            <word>Norwegian</word>
            <lemma>norwegian</lemma>
            <CharacterOffsetBegin>92</CharacterOffsetBegin>
            <CharacterOffsetEnd>101</CharacterOffsetEnd>
            <POS>JJ</POS>
          </token>
          <token id="18">
            <word>Seafood</word>
            <lemma>seafood</lemma>
            <CharacterOffsetBegin>102</CharacterOffsetBegin>
            <CharacterOffsetEnd>109</CharacterOffsetEnd>
            <POS>NN</POS>
          </token>
          <token id="19">
            <word>globally</word>
            <lemma>globally</lemma>
            <CharacterOffsetBegin>110</CharacterOffsetBegin>
            <CharacterOffsetEnd>118</CharacterOffsetEnd>
            <POS>RB</POS>
          </token>
          <token id="20">
            <word>.</word>
            <lemma>.</lemma>
            <CharacterOffsetBegin>118</CharacterOffsetBegin>
            <CharacterOffsetEnd>119</CharacterOffsetEnd>
            <POS>.</POS>
          </token>
          <token id="21">
            <word>''</word>
            <lemma>''</lemma>
            <CharacterOffsetBegin>119</CharacterOffsetBegin>
            <CharacterOffsetEnd>120</CharacterOffsetEnd>
            <POS>''</POS>
          </token>
        </tokens>
      </sentence>
      <sentence section="content" type="bodyText" id="12">
        <tokens>
          <token id="1">
            <word>WFS</word>
            <lemma>wfs</lemma>
            <CharacterOffsetBegin>0</CharacterOffsetBegin>
            <CharacterOffsetEnd>3</CharacterOffsetEnd>
            <POS>NN</POS>
          </token>
          <token id="2">
            <word>executive</word>
            <lemma>executive</lemma>
            <CharacterOffsetBegin>4</CharacterOffsetBegin>
            <CharacterOffsetEnd>13</CharacterOffsetEnd>
            <POS>NN</POS>
          </token>
          <token id="3">
            <word>vice</word>
            <lemma>vice</lemma>
            <CharacterOffsetBegin>14</CharacterOffsetBegin>
            <CharacterOffsetEnd>18</CharacterOffsetEnd>
            <POS>NN</POS>
          </token>
          <token id="4">
            <word>president</word>
            <lemma>president</lemma>
            <CharacterOffsetBegin>19</CharacterOffsetBegin>
            <CharacterOffsetEnd>28</CharacterOffsetEnd>
            <POS>NN</POS>
          </token>
          <token id="5">
            <word>cargo</word>
            <lemma>cargo</lemma>
            <CharacterOffsetBegin>29</CharacterOffsetBegin>
            <CharacterOffsetEnd>34</CharacterOffsetEnd>
            <POS>NN</POS>
          </token>
          <token id="6">
            <word>EMEAA</word>
            <lemma>EMEAA</lemma>
            <CharacterOffsetBegin>35</CharacterOffsetBegin>
            <CharacterOffsetEnd>40</CharacterOffsetEnd>
            <POS>NNP</POS>
          </token>
          <token id="7">
            <word>,</word>
            <lemma>,</lemma>
            <CharacterOffsetBegin>40</CharacterOffsetBegin>
            <CharacterOffsetEnd>41</CharacterOffsetEnd>
            <POS>,</POS>
          </token>
          <token id="8">
            <word>John</word>
            <lemma>John</lemma>
            <CharacterOffsetBegin>42</CharacterOffsetBegin>
            <CharacterOffsetEnd>46</CharacterOffsetEnd>
            <POS>NNP</POS>
          </token>
          <token id="9">
            <word>Batten</word>
            <lemma>Batten</lemma>
            <CharacterOffsetBegin>47</CharacterOffsetBegin>
            <CharacterOffsetEnd>53</CharacterOffsetEnd>
            <POS>NNP</POS>
          </token>
          <token id="10">
            <word>says</word>
            <lemma>say</lemma>
            <CharacterOffsetBegin>54</CharacterOffsetBegin>
            <CharacterOffsetEnd>58</CharacterOffsetEnd>
            <POS>VBZ</POS>
          </token>
          <token id="11">
            <word>:</word>
            <lemma>:</lemma>
            <CharacterOffsetBegin>58</CharacterOffsetBegin>
            <CharacterOffsetEnd>59</CharacterOffsetEnd>
            <POS>:</POS>
          </token>
          <token id="12">
            <word>``</word>
            <lemma>``</lemma>
            <CharacterOffsetBegin>60</CharacterOffsetBegin>
            <CharacterOffsetEnd>61</CharacterOffsetEnd>
            <POS>``</POS>
          </token>
          <token id="13">
            <word>The</word>
            <lemma>the</lemma>
            <CharacterOffsetBegin>61</CharacterOffsetBegin>
            <CharacterOffsetEnd>64</CharacterOffsetEnd>
            <POS>DT</POS>
          </token>
          <token id="14">
            <word>Seafood</word>
            <lemma>seafood</lemma>
            <CharacterOffsetBegin>65</CharacterOffsetBegin>
            <CharacterOffsetEnd>72</CharacterOffsetEnd>
            <POS>NN</POS>
          </token>
          <token id="15">
            <word>industry</word>
            <lemma>industry</lemma>
            <CharacterOffsetBegin>73</CharacterOffsetBegin>
            <CharacterOffsetEnd>81</CharacterOffsetEnd>
            <POS>NN</POS>
          </token>
          <token id="16">
            <word>is</word>
            <lemma>be</lemma>
            <CharacterOffsetBegin>82</CharacterOffsetBegin>
            <CharacterOffsetEnd>84</CharacterOffsetEnd>
            <POS>VBZ</POS>
          </token>
          <token id="17">
            <word>a</word>
            <lemma>a</lemma>
            <CharacterOffsetBegin>85</CharacterOffsetBegin>
            <CharacterOffsetEnd>86</CharacterOffsetEnd>
            <POS>DT</POS>
          </token>
          <token id="18">
            <word>unique</word>
            <lemma>unique</lemma>
            <CharacterOffsetBegin>87</CharacterOffsetBegin>
            <CharacterOffsetEnd>93</CharacterOffsetEnd>
            <POS>JJ</POS>
          </token>
          <token id="19">
            <word>opportunity</word>
            <lemma>opportunity</lemma>
            <CharacterOffsetBegin>94</CharacterOffsetBegin>
            <CharacterOffsetEnd>105</CharacterOffsetEnd>
            <POS>NN</POS>
          </token>
          <token id="20">
            <word>for</word>
            <lemma>for</lemma>
            <CharacterOffsetBegin>106</CharacterOffsetBegin>
            <CharacterOffsetEnd>109</CharacterOffsetEnd>
            <POS>IN</POS>
          </token>
          <token id="21">
            <word>us</word>
            <lemma>we</lemma>
            <CharacterOffsetBegin>110</CharacterOffsetBegin>
            <CharacterOffsetEnd>112</CharacterOffsetEnd>
            <POS>PRP</POS>
          </token>
          <token id="22">
            <word>to</word>
            <lemma>to</lemma>
            <CharacterOffsetBegin>113</CharacterOffsetBegin>
            <CharacterOffsetEnd>115</CharacterOffsetEnd>
            <POS>TO</POS>
          </token>
          <token id="23">
            <word>share</word>
            <lemma>share</lemma>
            <CharacterOffsetBegin>116</CharacterOffsetBegin>
            <CharacterOffsetEnd>121</CharacterOffsetEnd>
            <POS>VB</POS>
          </token>
          <token id="24">
            <word>our</word>
            <lemma>we</lemma>
            <CharacterOffsetBegin>122</CharacterOffsetBegin>
            <CharacterOffsetEnd>125</CharacterOffsetEnd>
            <POS>PRP$</POS>
          </token>
          <token id="25">
            <word>experience</word>
            <lemma>experience</lemma>
            <CharacterOffsetBegin>126</CharacterOffsetBegin>
            <CharacterOffsetEnd>136</CharacterOffsetEnd>
            <POS>NN</POS>
          </token>
          <token id="26">
            <word>and</word>
            <lemma>and</lemma>
            <CharacterOffsetBegin>137</CharacterOffsetBegin>
            <CharacterOffsetEnd>140</CharacterOffsetEnd>
            <POS>CC</POS>
          </token>
          <token id="27">
            <word>excellence</word>
            <lemma>excellence</lemma>
            <CharacterOffsetBegin>141</CharacterOffsetBegin>
            <CharacterOffsetEnd>151</CharacterOffsetEnd>
            <POS>NN</POS>
          </token>
          <token id="28">
            <word>in</word>
            <lemma>in</lemma>
            <CharacterOffsetBegin>152</CharacterOffsetBegin>
            <CharacterOffsetEnd>154</CharacterOffsetEnd>
            <POS>IN</POS>
          </token>
          <token id="29">
            <word>air</word>
            <lemma>air</lemma>
            <CharacterOffsetBegin>155</CharacterOffsetBegin>
            <CharacterOffsetEnd>158</CharacterOffsetEnd>
            <POS>NN</POS>
          </token>
          <token id="30">
            <word>cargo</word>
            <lemma>cargo</lemma>
            <CharacterOffsetBegin>159</CharacterOffsetBegin>
            <CharacterOffsetEnd>164</CharacterOffsetEnd>
            <POS>NN</POS>
          </token>
          <token id="31">
            <word>handling</word>
            <lemma>handling</lemma>
            <CharacterOffsetBegin>165</CharacterOffsetBegin>
            <CharacterOffsetEnd>173</CharacterOffsetEnd>
            <POS>NN</POS>
          </token>
          <token id="32">
            <word>.</word>
            <lemma>.</lemma>
            <CharacterOffsetBegin>173</CharacterOffsetBegin>
            <CharacterOffsetEnd>174</CharacterOffsetEnd>
            <POS>.</POS>
          </token>
        </tokens>
      </sentence>
      <sentence section="content" type="bodyText" id="13">
        <tokens>
          <token id="1">
            <word>We</word>
            <lemma>we</lemma>
            <CharacterOffsetBegin>175</CharacterOffsetBegin>
            <CharacterOffsetEnd>177</CharacterOffsetEnd>
            <POS>PRP</POS>
          </token>
          <token id="2">
            <word>look</word>
            <lemma>look</lemma>
            <CharacterOffsetBegin>178</CharacterOffsetBegin>
            <CharacterOffsetEnd>182</CharacterOffsetEnd>
            <POS>VBP</POS>
          </token>
          <token id="3">
            <word>forward</word>
            <lemma>forward</lemma>
            <CharacterOffsetBegin>183</CharacterOffsetBegin>
            <CharacterOffsetEnd>190</CharacterOffsetEnd>
            <POS>RB</POS>
          </token>
          <token id="4">
            <word>to</word>
            <lemma>to</lemma>
            <CharacterOffsetBegin>191</CharacterOffsetBegin>
            <CharacterOffsetEnd>193</CharacterOffsetEnd>
            <POS>TO</POS>
          </token>
          <token id="5">
            <word>opening</word>
            <lemma>open</lemma>
            <CharacterOffsetBegin>194</CharacterOffsetBegin>
            <CharacterOffsetEnd>201</CharacterOffsetEnd>
            <POS>VBG</POS>
          </token>
          <token id="6">
            <word>a</word>
            <lemma>a</lemma>
            <CharacterOffsetBegin>202</CharacterOffsetBegin>
            <CharacterOffsetEnd>203</CharacterOffsetEnd>
            <POS>DT</POS>
          </token>
          <token id="7">
            <word>dedicated</word>
            <lemma>dedicated</lemma>
            <CharacterOffsetBegin>204</CharacterOffsetBegin>
            <CharacterOffsetEnd>213</CharacterOffsetEnd>
            <POS>JJ</POS>
          </token>
          <token id="8">
            <word>facility</word>
            <lemma>facility</lemma>
            <CharacterOffsetBegin>214</CharacterOffsetBegin>
            <CharacterOffsetEnd>222</CharacterOffsetEnd>
            <POS>NN</POS>
          </token>
          <token id="9">
            <word>at</word>
            <lemma>at</lemma>
            <CharacterOffsetBegin>223</CharacterOffsetBegin>
            <CharacterOffsetEnd>225</CharacterOffsetEnd>
            <POS>IN</POS>
          </token>
          <token id="10">
            <word>Oslo</word>
            <lemma>Oslo</lemma>
            <CharacterOffsetBegin>226</CharacterOffsetBegin>
            <CharacterOffsetEnd>230</CharacterOffsetEnd>
            <POS>NNP</POS>
          </token>
          <token id="11">
            <word>Airport</word>
            <lemma>Airport</lemma>
            <CharacterOffsetBegin>231</CharacterOffsetBegin>
            <CharacterOffsetEnd>238</CharacterOffsetEnd>
            <POS>NNP</POS>
          </token>
          <token id="12">
            <word>that</word>
            <lemma>that</lemma>
            <CharacterOffsetBegin>239</CharacterOffsetBegin>
            <CharacterOffsetEnd>243</CharacterOffsetEnd>
            <POS>WDT</POS>
          </token>
          <token id="13">
            <word>is</word>
            <lemma>be</lemma>
            <CharacterOffsetBegin>244</CharacterOffsetBegin>
            <CharacterOffsetEnd>246</CharacterOffsetEnd>
            <POS>VBZ</POS>
          </token>
          <token id="14">
            <word>fully</word>
            <lemma>fully</lemma>
            <CharacterOffsetBegin>247</CharacterOffsetBegin>
            <CharacterOffsetEnd>252</CharacterOffsetEnd>
            <POS>RB</POS>
          </token>
          <token id="15">
            <word>adapted</word>
            <lemma>adapt</lemma>
            <CharacterOffsetBegin>253</CharacterOffsetBegin>
            <CharacterOffsetEnd>260</CharacterOffsetEnd>
            <POS>VBN</POS>
          </token>
          <token id="16">
            <word>to</word>
            <lemma>to</lemma>
            <CharacterOffsetBegin>261</CharacterOffsetBegin>
            <CharacterOffsetEnd>263</CharacterOffsetEnd>
            <POS>TO</POS>
          </token>
          <token id="17">
            <word>the</word>
            <lemma>the</lemma>
            <CharacterOffsetBegin>264</CharacterOffsetBegin>
            <CharacterOffsetEnd>267</CharacterOffsetEnd>
            <POS>DT</POS>
          </token>
          <token id="18">
            <word>future</word>
            <lemma>future</lemma>
            <CharacterOffsetBegin>268</CharacterOffsetBegin>
            <CharacterOffsetEnd>274</CharacterOffsetEnd>
            <POS>JJ</POS>
          </token>
          <token id="19">
            <word>needs</word>
            <lemma>need</lemma>
            <CharacterOffsetBegin>275</CharacterOffsetBegin>
            <CharacterOffsetEnd>280</CharacterOffsetEnd>
            <POS>NNS</POS>
          </token>
          <token id="20">
            <word>of</word>
            <lemma>of</lemma>
            <CharacterOffsetBegin>281</CharacterOffsetBegin>
            <CharacterOffsetEnd>283</CharacterOffsetEnd>
            <POS>IN</POS>
          </token>
          <token id="21">
            <word>the</word>
            <lemma>the</lemma>
            <CharacterOffsetBegin>284</CharacterOffsetBegin>
            <CharacterOffsetEnd>287</CharacterOffsetEnd>
            <POS>DT</POS>
          </token>
          <token id="22">
            <word>Seafood</word>
            <lemma>seafood</lemma>
            <CharacterOffsetBegin>288</CharacterOffsetBegin>
            <CharacterOffsetEnd>295</CharacterOffsetEnd>
            <POS>NN</POS>
          </token>
          <token id="23">
            <word>industry</word>
            <lemma>industry</lemma>
            <CharacterOffsetBegin>296</CharacterOffsetBegin>
            <CharacterOffsetEnd>304</CharacterOffsetEnd>
            <POS>NN</POS>
          </token>
          <token id="24">
            <word>.</word>
            <lemma>.</lemma>
            <CharacterOffsetBegin>304</CharacterOffsetBegin>
            <CharacterOffsetEnd>305</CharacterOffsetEnd>
            <POS>.</POS>
          </token>
        </tokens>
      </sentence>
      <sentence section="content" type="bodyText" id="14">
        <tokens>
          <token id="1">
            <word>``</word>
            <lemma>``</lemma>
            <CharacterOffsetBegin>0</CharacterOffsetBegin>
            <CharacterOffsetEnd>1</CharacterOffsetEnd>
            <POS>``</POS>
          </token>
          <token id="2">
            <word>Our</word>
            <lemma>we</lemma>
            <CharacterOffsetBegin>1</CharacterOffsetBegin>
            <CharacterOffsetEnd>4</CharacterOffsetEnd>
            <POS>PRP$</POS>
          </token>
          <token id="3">
            <word>terminal</word>
            <lemma>terminal</lemma>
            <CharacterOffsetBegin>5</CharacterOffsetBegin>
            <CharacterOffsetEnd>13</CharacterOffsetEnd>
            <POS>NN</POS>
          </token>
          <token id="4">
            <word>will</word>
            <lemma>will</lemma>
            <CharacterOffsetBegin>14</CharacterOffsetBegin>
            <CharacterOffsetEnd>18</CharacterOffsetEnd>
            <POS>MD</POS>
          </token>
          <token id="5">
            <word>be</word>
            <lemma>be</lemma>
            <CharacterOffsetBegin>19</CharacterOffsetBegin>
            <CharacterOffsetEnd>21</CharacterOffsetEnd>
            <POS>VB</POS>
          </token>
          <token id="6">
            <word>a</word>
            <lemma>a</lemma>
            <CharacterOffsetBegin>22</CharacterOffsetBegin>
            <CharacterOffsetEnd>23</CharacterOffsetEnd>
            <POS>DT</POS>
          </token>
          <token id="7">
            <word>game</word>
            <lemma>game</lemma>
            <CharacterOffsetBegin>24</CharacterOffsetBegin>
            <CharacterOffsetEnd>28</CharacterOffsetEnd>
            <POS>NN</POS>
          </token>
          <token id="8">
            <word>changer</word>
            <lemma>changer</lemma>
            <CharacterOffsetBegin>29</CharacterOffsetBegin>
            <CharacterOffsetEnd>36</CharacterOffsetEnd>
            <POS>NN</POS>
          </token>
          <token id="9">
            <word>in</word>
            <lemma>in</lemma>
            <CharacterOffsetBegin>37</CharacterOffsetBegin>
            <CharacterOffsetEnd>39</CharacterOffsetEnd>
            <POS>IN</POS>
          </token>
          <token id="10">
            <word>the</word>
            <lemma>the</lemma>
            <CharacterOffsetBegin>40</CharacterOffsetBegin>
            <CharacterOffsetEnd>43</CharacterOffsetEnd>
            <POS>DT</POS>
          </token>
          <token id="11">
            <word>handling</word>
            <lemma>handling</lemma>
            <CharacterOffsetBegin>44</CharacterOffsetBegin>
            <CharacterOffsetEnd>52</CharacterOffsetEnd>
            <POS>NN</POS>
          </token>
          <token id="12">
            <word>of</word>
            <lemma>of</lemma>
            <CharacterOffsetBegin>53</CharacterOffsetBegin>
            <CharacterOffsetEnd>55</CharacterOffsetEnd>
            <POS>IN</POS>
          </token>
          <token id="13">
            <word>Seafood</word>
            <lemma>Seafood</lemma>
            <CharacterOffsetBegin>56</CharacterOffsetBegin>
            <CharacterOffsetEnd>63</CharacterOffsetEnd>
            <POS>NNP</POS>
          </token>
          <token id="14">
            <word>as</word>
            <lemma>as</lemma>
            <CharacterOffsetBegin>64</CharacterOffsetBegin>
            <CharacterOffsetEnd>66</CharacterOffsetEnd>
            <POS>IN</POS>
          </token>
          <token id="15">
            <word>air</word>
            <lemma>air</lemma>
            <CharacterOffsetBegin>67</CharacterOffsetBegin>
            <CharacterOffsetEnd>70</CharacterOffsetEnd>
            <POS>NN</POS>
          </token>
          <token id="16">
            <word>cargo</word>
            <lemma>cargo</lemma>
            <CharacterOffsetBegin>71</CharacterOffsetBegin>
            <CharacterOffsetEnd>76</CharacterOffsetEnd>
            <POS>NN</POS>
          </token>
          <token id="17">
            <word>and</word>
            <lemma>and</lemma>
            <CharacterOffsetBegin>77</CharacterOffsetBegin>
            <CharacterOffsetEnd>80</CharacterOffsetEnd>
            <POS>CC</POS>
          </token>
          <token id="18">
            <word>be</word>
            <lemma>be</lemma>
            <CharacterOffsetBegin>81</CharacterOffsetBegin>
            <CharacterOffsetEnd>83</CharacterOffsetEnd>
            <POS>VB</POS>
          </token>
          <token id="19">
            <word>an</word>
            <lemma>a</lemma>
            <CharacterOffsetBegin>84</CharacterOffsetBegin>
            <CharacterOffsetEnd>86</CharacterOffsetEnd>
            <POS>DT</POS>
          </token>
          <token id="20">
            <word>important</word>
            <lemma>important</lemma>
            <CharacterOffsetBegin>87</CharacterOffsetBegin>
            <CharacterOffsetEnd>96</CharacterOffsetEnd>
            <POS>JJ</POS>
          </token>
          <token id="21">
            <word>part</word>
            <lemma>part</lemma>
            <CharacterOffsetBegin>97</CharacterOffsetBegin>
            <CharacterOffsetEnd>101</CharacterOffsetEnd>
            <POS>NN</POS>
          </token>
          <token id="22">
            <word>of</word>
            <lemma>of</lemma>
            <CharacterOffsetBegin>102</CharacterOffsetBegin>
            <CharacterOffsetEnd>104</CharacterOffsetEnd>
            <POS>IN</POS>
          </token>
          <token id="23">
            <word>ensuring</word>
            <lemma>ensure</lemma>
            <CharacterOffsetBegin>105</CharacterOffsetBegin>
            <CharacterOffsetEnd>113</CharacterOffsetEnd>
            <POS>VBG</POS>
          </token>
          <token id="24">
            <word>the</word>
            <lemma>the</lemma>
            <CharacterOffsetBegin>114</CharacterOffsetBegin>
            <CharacterOffsetEnd>117</CharacterOffsetEnd>
            <POS>DT</POS>
          </token>
          <token id="25">
            <word>future</word>
            <lemma>future</lemma>
            <CharacterOffsetBegin>118</CharacterOffsetBegin>
            <CharacterOffsetEnd>124</CharacterOffsetEnd>
            <POS>JJ</POS>
          </token>
          <token id="26">
            <word>growth</word>
            <lemma>growth</lemma>
            <CharacterOffsetBegin>125</CharacterOffsetBegin>
            <CharacterOffsetEnd>131</CharacterOffsetEnd>
            <POS>NN</POS>
          </token>
          <token id="27">
            <word>of</word>
            <lemma>of</lemma>
            <CharacterOffsetBegin>132</CharacterOffsetBegin>
            <CharacterOffsetEnd>134</CharacterOffsetEnd>
            <POS>IN</POS>
          </token>
          <token id="28">
            <word>one</word>
            <lemma>one</lemma>
            <CharacterOffsetBegin>135</CharacterOffsetBegin>
            <CharacterOffsetEnd>138</CharacterOffsetEnd>
            <POS>CD</POS>
          </token>
          <token id="29">
            <word>of</word>
            <lemma>of</lemma>
            <CharacterOffsetBegin>139</CharacterOffsetBegin>
            <CharacterOffsetEnd>141</CharacterOffsetEnd>
            <POS>IN</POS>
          </token>
          <token id="30">
            <word>Norway</word>
            <lemma>Norway</lemma>
            <CharacterOffsetBegin>142</CharacterOffsetBegin>
            <CharacterOffsetEnd>148</CharacterOffsetEnd>
            <POS>NNP</POS>
          </token>
          <token id="31">
            <word>'s</word>
            <lemma>'s</lemma>
            <CharacterOffsetBegin>148</CharacterOffsetBegin>
            <CharacterOffsetEnd>150</CharacterOffsetEnd>
            <POS>POS</POS>
          </token>
          <token id="32">
            <word>most</word>
            <lemma>most</lemma>
            <CharacterOffsetBegin>151</CharacterOffsetBegin>
            <CharacterOffsetEnd>155</CharacterOffsetEnd>
            <POS>RBS</POS>
          </token>
          <token id="33">
            <word>important</word>
            <lemma>important</lemma>
            <CharacterOffsetBegin>156</CharacterOffsetBegin>
            <CharacterOffsetEnd>165</CharacterOffsetEnd>
            <POS>JJ</POS>
          </token>
          <token id="34">
            <word>industries</word>
            <lemma>industry</lemma>
            <CharacterOffsetBegin>166</CharacterOffsetBegin>
            <CharacterOffsetEnd>176</CharacterOffsetEnd>
            <POS>NNS</POS>
          </token>
          <token id="35">
            <word>.</word>
            <lemma>.</lemma>
            <CharacterOffsetBegin>176</CharacterOffsetBegin>
            <CharacterOffsetEnd>177</CharacterOffsetEnd>
            <POS>.</POS>
          </token>
          <token id="36">
            <word>''</word>
            <lemma>''</lemma>
            <CharacterOffsetBegin>177</CharacterOffsetBegin>
            <CharacterOffsetEnd>178</CharacterOffsetEnd>
            <POS>''</POS>
          </token>
        </tokens>
      </sentence>
    </sentences>
  </document>
</root>
